Workbook

Sheet Report
D1: Sheet Validation | J1: =IF(SUM(AF:AF)=0,"SHEET NOT YET STARTED",IF(SUM(AG:AG)>0,"SHEET NOT COMPLETE","SHEET COMPLETE")) -> SHEET COMPLETE
D3: Report | AB3: Comments for Surveyors | AD3: Visibility | AE3: Sheet Validation to right | AF3: Check if any data is entered | AG3: Check if field needs to be completed
A4: =IF(AG4=1,"X","") | B4: 1 | AD4: Always show
A5: =IF(AG5=1,"X","") | B5: 1 | AD5: Always show
A6: =IF(AG6=1,"X","") | B6: 1 | D6: Client Name And Site Details | AB6: Will always show | AD6: Always show
A7: =IF(AG7=1,"X","") | B7: 1 | AD7: Always show
A8: =IF(AG8=1,"X","") | B8: 1 | D8: =Costing!E7 -> Finest Properties | AB8: Will always show (pre-populated) | AD8: Always show | AF8: =IF(D8<>"",1,0) -> 1 | AG8: =IF(AND(SUM(AF:AF)>0,OR(D8="",D8=0)),1,0) -> 0
A9: =IF(AG9=1,"X","") | B9: 1 | D9: =Costing!E8 -> Clive House | AB9: Will always show (pre-populated) | AD9: Always show | AF9: =IF(D9<>"",1,0) -> 1 | AG9: =IF(AND(SUM(AF:AF)>0,OR(D9="",D9=0)),1,0) -> 0
A10: =IF(AG10=1,"X","") | B10: 1 | D10: =Costing!E9 -> Appletree Lane | AB10: Will always show (pre-populated) | AD10: Always show | AF10: =IF(D10<>"",1,0) -> 1 | AG10: =IF(AND(SUM(AF:AF)>0,OR(D10="",D10=0)),1,0) -> 0
A11: =IF(AG11=1,"X","") | B11: 1 | D11: =Costing!E10 -> Corbridge | AB11: Will always show (pre-populated) | AD11: Always show | AF11: =IF(D11<>"",1,0) -> 1 | AG11: =IF(AND(SUM(AF:AF)>0,OR(D11="",D11=0)),1,0) -> 0
A12: =IF(AG12=1,"X","") | B12: 1 | D12: =Costing!E11 -> NE45 5DN | AB12: Will always show (pre-populated) | AD12: Always show | AF12: =IF(D12<>"",1,0) -> 1 | AG12: =IF(AND(SUM(AF:AF)>0,OR(D12="",D12=0)),1,0) -> 0
A13: =IF(AG13=1,"X","") | B13: 1 | D13: Internal Reference ID: | I13: =Costing!E4 -> PRONE455DN | AB13: Will always show (pre-populated) | AD13: Always show | AF13: =IF(I13<>"",1,0) -> 1 | AG13: =IF(AND(SUM(AF:AF)>0,OR(I13="",I13=0)),1,0) -> 0
A14: =IF(AG14=1,"X","") | B14: 1 | AD14: Always show
A15: =IF(AG15=1,"X","") | B15: 1 | AD15: Always show
A16: =IF(AG16=1,"X","") | B16: 1 | D16: Weather Conditions | AB16: Will always show | AD16: Always show
A17: =IF(AG17=1,"X","") | B17: 1 | D17: Date of Inspection: | K17: 45982 | AB17: ← Enter Data Here | AD17: Always show | AF17: =IF(K17<>"",1,0) -> 1 | AG17: =IF(AND(SUM(AF:AF)>0,K17=""),1,0) -> 0
A18: =IF(AG18=1,"X","") | B18: 1 | D18: The weather conditions were: | K18: Dry sunny | AB18: ← Enter Data Here | AD18: Always show | AF18: =IF(K18<>"",1,0) -> 1 | AG18: =IF(AND(SUM(AF:AF)>0,K18=""),1,0) -> 0
A19: =IF(AG19=1,"X","") | B19: 1 | D19: The weather temperature was: | K19: 3 | L19: (°C). | AB19: ← Enter Data Here | AD19: Always show | AF19: =IF(K19<>"",1,0) -> 1 | AG19: =IF(AND(SUM(AF:AF)>0,K19=""),1,0) -> 0
A20: =IF(AG20=1,"X","") | B20: 1 | D20: The Property | AB20: Will always show | AD20: Always show
A21: =IF(AG21=1,"X","") | B21: 0 | D21: Use the alt key and the mouse to 'snap' the image to the top and bottom of the cell for alignment. | AB21: This line will NOT show on the report | AD21: Always Hide
B22: 0 | D22: ↓ Image Section 1 ↓ | AB22: This line will NOT show on the report | AD22: Always Hide
A23: =IF(AG23=1,"X","") | B23: =IF(OR(D24="Show",Q24="Show"),1,0) -> 1 | AD23: Always show
A24: =IF(AG24=1,"X","") | B24: 0 | D24: Show | Q24: Show | AB24: ← Enter Image Visibility | AD24: Determined by surveyor | AF24: =IF(OR(D24="Show",D24="",Q24="Show",Q24=""),1,0) -> 1 | AG24: =IF(AND(SUM(AF:AF)>0,OR(D24="",Q24="")),1,0) -> 0
A25: =IF(AG25=1,"X","") | B25: =B23 -> 1 | AB25: ← Add Images | AD25: Determined by surveyor
A26: =IF(AG26=1,"X","") | B26: =B25 -> 1 | D26: Front Elevation | Q26: Side Elevation | AB26: ← Enter Images Descriptions | AD26: Determined by surveyor | AF26: =IF(OR(D24="Show",D24="",Q24="Show",Q24=""),1,0) -> 1 | AG26: =IF(AND(SUM(AF:AF)>0,OR(AND(D24="Show",D26=""),AND(Q24="Show",Q26=""))),1,0) -> 0
A27: =IF(AG27=1,"X","") | B27: =B26 -> 1 | AD27: Always show
B28: 0 | D28: ↑ Image Section 1 ↑ | AB28: This line will NOT show on the report | AD28: Always Hide
B29: 0 | D29: ↓ Image Section 1 ↓ | AB29: This line will NOT show on the report | AD29: Always Hide
A30: =IF(AG30=1,"X","") | B30: =IF(OR(D31="Show",Q31="Show"),1,0) -> 1 | AD30: Always show
A31: =IF(AG31=1,"X","") | B31: 0 | D31: Show | Q31: Hide | AB31: ← Enter Image Visibility | AD31: Determined by surveyor | AF31: =IF(OR(D31="Show",D31="",Q31="Show",Q31=""),1,0) -> 1 | AG31: =IF(AND(SUM(AF:AF)>0,OR(D31="",Q31="")),1,0) -> 0
A32: =IF(AG32=1,"X","") | B32: =B30 -> 1 | AB32: ← Add Images | AD32: Determined by surveyor
A33: =IF(AG33=1,"X","") | B33: =B32 -> 1 | D33: Ensuite | AB33: ← Enter Images Descriptions | AD33: Determined by surveyor | AF33: =IF(OR(D31="Show",D31="",Q31="Show",Q31=""),1,0) -> 1 | AG33: =IF(AND(SUM(AF:AF)>0,OR(AND(D31="Show",D33=""),AND(Q31="Show",Q33=""))),1,0) -> 0
A34: =IF(AG34=1,"X","") | B34: =B33 -> 1 | AD34: Always show
B35: 0 | D35: ↑ Image Section 1 ↑ | AB35: This line will NOT show on the report | AD35: Always Hide
A36: =IF(AG36=1,"X","") | B36: 1 | D36: The property is a: | M36: Stone and slate | AB36: ← Enter Data Here | AD36: Always show | AF36: =IF(M36<>"",1,0) -> 1 | AG36: =IF(AND(SUM(AF:AF)>0,M36=""),1,0) -> 0
A37: =IF(AG37=1,"X","") | B37: 1 | D37: The property is constructed of : | M37: Detached | AB37: ← Enter Data Here | AD37: Always show | AF37: =IF(M37<>"",1,0) -> 1 | AG37: =IF(AND(SUM(AF:AF)>0,M37=""),1,0) -> 0
A38: =IF(AG38=1,"X","") | B38: 1 | D38: The property was built approximately : | M38: 1800s | AB38: ← Enter Data Here | AD38: Always show | AF38: =IF(M38<>"",1,0) -> 1 | AG38: =IF(AND(SUM(AF:AF)>0,M38=""),1,0) -> 0
A39: =IF(AG39=1,"X","") | B39: 1 | D39: The Survey/Specific Defects Inspection | AB39: Will always show | AD39: Always show
A40: =IF(AG40=1,"X","") | B40: 1 | D40: In accordance with your specific instructions, we carried out a survey of the above property for problems with mould, mildew & condensation. | AB40: Will always show | AD40: Always show
A41: =IF(AG41=1,"X","") | B41: 1 | D41: Our findings and proposals are set out below and should be read in conjunction with the enclosed document 'General Notes for clients and Health and Safety precautions'. | AB41: Will always show | AD41: Always show
A42: =IF(AG42=1,"X","") | B42: 1 | D42: Orientation | AB42: Will always show | AD42: Always show
A43: =IF(AG43=1,"X","") | B43: 1 | D43: The terms left, right, front and rear are used in accordance with facing the front elevation from the outside of the building. | AB43: Will always show | AD43: Always show
A44: =IF(AG44=1,"X","") | B44: 1 | D44: The Scope | AB44: Will always show | AD44: Always show
A45: =IF(AG45=1,"X","") | B45: 1 | D45: Our specific defects inspection was solely to identify evidence of problems that you have requested us to inspect which was that of mould and condensation within the above property. | AB45: Will always show | AD45: Always show
A46: =IF(AG46=1,"X","") | B46: 1 | D46: Abbreviations Used In Report | AB46: Will always show | AD46: Always show
A47: =IF(AG47=1,"X","") | B47: 1 | D47: PIV = Positive Input Ventilation, ACM's = Asbestos containing materials. | AB47: Will always show | AD47: Always show
A48: =IF(AG48=1,"X","") | B48: 1 | D48: Internal Inspection | AB48: ← Enter Visibility | AD48: Determined by surveyor
A49: =IF(AG49=1,"X","") | B49: 1 | D49: During the internal inspection the following issues were noted: | AB49: ← Enter Visibility | AD49: Determined by surveyor | AF49: =IF(B49<>"",1,0) -> 1 | AG49: =IF(AND(SUM(AF:AF)>0,B49=""),1,0) -> 0
A50: =IF(AG50=1,"X","") | B50: 0 | D50: • | E50: Condensation, was apparent on the windows. | AB50: ← Enter Visibility | AD50: Determined by surveyor | AF50: =IF(B50<>"",1,0) -> 1 | AG50: =IF(AND(SUM(AF:AF)>0,B50=""),1,0) -> 0
A51: =IF(AG51=1,"X","") | B51: 1 | D51: • | E51: Areas of low temperature/poor air movement to the walls creating dew points. | AB51: ← Enter Visibility | AD51: Determined by surveyor | AF51: =IF(B51<>"",1,0) -> 1 | AG51: =IF(AND(SUM(AF:AF)>0,B51=""),1,0) -> 0
A52: =IF(AG52=1,"X","") | B52: 1 | D52: • | E52: Black spot mould was present within the building. | AB52: ← Enter Visibility | AD52: Determined by surveyor | AF52: =IF(B52<>"",1,0) -> 1 | AG52: =IF(AND(SUM(AF:AF)>0,B52=""),1,0) -> 0
A53: =IF(AG53=1,"X","") | B53: 1 | D53: • | E53: There was a lack of ventilation and air movement within the property. | AB53: ← Enter Visibility | AD53: Determined by surveyor | AF53: =IF(B53<>"",1,0) -> 1 | AG53: =IF(AND(SUM(AF:AF)>0,B53=""),1,0) -> 0
A54: =IF(AG54=1,"X","") | B54: 1 | D54: • | E54: We suspect poor insulation values due to solid brick walls. | AB54: ← Enter Visibility | AD54: Determined by surveyor | AF54: =IF(B54<>"",1,0) -> 1 | AG54: =IF(AND(SUM(AF:AF)>0,B54=""),1,0) -> 0
A55: =IF(AG55=1,"X","") | B55: 1 | D55: • | E55: Humidity readings were taken within the property, these readings peaked at | W55: 95 | Y55: %. | AB55: ← Enter humidity % Data Here | AD55: Determined by surveyor | AF55: =IF(OR(B55<>"",P55<>""),1,0) -> 1 | AG55: =IF(AND(SUM(AF:AF)>0,OR(AND(B55=1,W55=""),AND(B55="",W55=""),AND(B55="",W55<>""),AND(B55=0,W55<>""))),1,0) -> 0
A56: =IF(AG56=1,"X","") | B56: 0 | D56: • | E56: Other not covered by above - (state below) | AB56: This line will NOT show on the report | AD56: Always Hide
A57: =IF(AG57=1,"X","") | B57: 1 | D57: • | E57: Staining was noted to the ceiling below the main bathroom and black mould to a cold external wall. The mould to the wall is not related to the bathroom or the ceiling. | AB57: ← Enter Visibility & Data | AD57: Determined by surveyor | AF57: =IF(B57<>"",1,0) -> 1 | AG57: =IF(AND(SUM(AF:AF)>0,OR(AND(B57=1,E57=""),AND(B57="",E57=""),AND(B57="",E57<>""),AND(B57=0,E57<>""))),1,0) -> 0
A58: =IF(AG58=1,"X","") | B58: 1 | D58: • | E58: Plumber to inspect and repair any leaks / damage to the ensuite | AB58: ← Enter Visibility & Data | AD58: Determined by surveyor | AF58: =IF(B58<>"",1,0) -> 1 | AG58: =IF(AND(SUM(AF:AF)>0,OR(AND(B58=1,E58=""),AND(B58="",E58=""),AND(B58="",E58<>""),AND(B58=0,E58<>""))),1,0) -> 0
A59: =IF(AG59=1,"X","") | B59: 0 | D59: • | AB59: ← Enter Visibility & Data | AD59: Determined by surveyor | AF59: =IF(B59<>"",1,0) -> 1 | AG59: =IF(AND(SUM(AF:AF)>0,OR(AND(B59=1,E59=""),AND(B59="",E59=""),AND(B59="",E59<>""),AND(B59=0,E59<>""))),1,0) -> 0
A60: =IF(AG60=1,"X","") | B60: 0 | D60: Use the alt key and the mouse to 'snap' the image to the top and bottom of the cell for alignment. | AB60: This line will NOT show on the report | AD60: Always Hide
B61: 0 | D61: ↓ Image Section 1 ↓ | AB61: This line will NOT show on the report | AD61: Always Hide
A62: =IF(AG62=1,"X","") | B62: =IF(OR(D63="Show",Q63="Show"),1,0) -> 1 | AD62: Always show
A63: =IF(AG63=1,"X","") | B63: 0 | D63: Show | Q63: Show | AB63: ← Enter Image Visibility | AD63: Determined by surveyor | AF63: =IF(OR(D63="Show",D63="",Q63="Show",Q63=""),1,0) -> 1 | AG63: =IF(AND(SUM(AF:AF)>0,OR(D63="",Q63="")),1,0) -> 0
A64: =IF(AG64=1,"X","") | B64: =B62 -> 1 | AB64: ← Add Images | AD64: Determined by surveyor
A65: =IF(AG65=1,"X","") | B65: =B64 -> 1 | D65: High humidity | Q65: High humidity | AB65: ← Enter Images Descriptions | AD65: Determined by surveyor | AF65: =IF(OR(D63="Show",D63="",Q63="Show",Q63=""),1,0) -> 1 | AG65: =IF(AND(SUM(AF:AF)>0,OR(AND(D63="Show",D65=""),AND(Q63="Show",Q65=""))),1,0) -> 0
A66: =IF(AG66=1,"X","") | B66: =B65 -> 1 | AD66: Always show
B67: 0 | D67: ↑ Image Section 1 ↑ | AB67: This line will NOT show on the report | AD67: Always Hide
B68: 0 | D68: ↓ Image Section 2 ↓ | AB68: This line will NOT show on the report | AD68: Always Hide
A69: =IF(AG69=1,"X","") | B69: =IF(OR(D70="Show",Q70="Show"),1,0) -> 1 | AD69: Always show
A70: =IF(AG70=1,"X","") | B70: 0 | D70: Show | Q70: Show | AB70: ← Enter Image Visibility | AD70: Determined by surveyor | AF70: =IF(OR(D70="Show",D70="",Q70="Show",Q70=""),1,0) -> 1 | AG70: =IF(AND(SUM(AF:AF)>0,OR(D70="",Q70="")),1,0) -> 0
A71: =IF(AG71=1,"X","") | B71: =B69 -> 1 | AB71: ← Add Images | AD71: Determined by surveyor
A72: =IF(AG72=1,"X","") | B72: =B71 -> 1 | D72: Main Bedroom | Q72: Bedroom | AB72: ← Enter Images Descriptions | AD72: Determined by surveyor | AF72: =IF(OR(D70="Show",D70="",Q70="Show",Q70=""),1,0) -> 1 | AG72: =IF(AND(SUM(AF:AF)>0,OR(AND(D70="Show",D72=""),AND(Q70="Show",Q72=""))),1,0) -> 0
A73: =IF(AG73=1,"X","") | B73: =B72 -> 1 | AD73: Always show
B74: 0 | D74: ↑ Image Section 2 ↑ | AB74: This line will NOT show on the report | AD74: Always Hide
B75: 0 | D75: ↓ Image Section 3 ↓ | AB75: This line will NOT show on the report | AD75: Always Hide
A76: =IF(AG76=1,"X","") | B76: =IF(OR(D77="Show",Q77="Show"),1,0) -> 0 | AD76: Always show
A77: =IF(AG77=1,"X","") | B77: 0 | D77: Hide | Q77: Hide | AB77: ← Enter Image Visibility | AD77: Determined by surveyor | AF77: =IF(OR(D77="Show",D77="",Q77="Show",Q77=""),1,0) -> 0 | AG77: =IF(AND(SUM(AF:AF)>0,OR(D77="",Q77="")),1,0) -> 0
A78: =IF(AG78=1,"X","") | B78: =B76 -> 0 | AB78: ← Add Images | AD78: Determined by surveyor
A79: =IF(AG79=1,"X","") | B79: =B78 -> 0 | AB79: ← Enter Images Descriptions | AD79: Determined by surveyor | AF79: =IF(OR(D77="Show",D77="",Q77="Show",Q77=""),1,0) -> 0 | AG79: =IF(AND(SUM(AF:AF)>0,OR(AND(D77="Show",D79=""),AND(Q77="Show",Q79=""))),1,0) -> 0
A80: =IF(AG80=1,"X","") | B80: =B79 -> 0 | AD80: Always show
B81: 0 | D81: ↑ Image Section 3 ↑ | AB81: This line will NOT show on the report | AD81: Always Hide
A82: =IF(AG82=1,"X","") | B82: 1 | AD82: Always show
A83: =IF(AG83=1,"X","") | B83: 1 | D83: The above problems have been caused by: | AB83: ← Enter Visibility | AD83: Determined by surveyor
A84: =IF(AG84=1,"X","") | B84: 0 | D84: • | E84: A lack of ventilation and air movement within the property. | AB84: ← Enter Visibility | AD84: Determined by surveyor | AF84: =IF(B84<>"",1,0) -> 1 | AG84: =IF(AND(SUM(AF:AF)>0,B84=""),1,0) -> 0
A85: =IF(AG85=1,"X","") | B85: 0 | D85: • | E85: Poor insulation values of solid brick walls. | AB85: ← Enter Visibility | AD85: Determined by surveyor | AF85: =IF(B85<>"",1,0) -> 1 | AG85: =IF(AND(SUM(AF:AF)>0,B85=""),1,0) -> 0
A86: =IF(AG86=1,"X","") | B86: 0 | D86: • | E86: Dampness within the fabric of the building. | AB86: ← Enter Visibility | AD86: Determined by surveyor | AF86: =IF(B86<>"",1,0) -> 1 | AG86: =IF(AND(SUM(AF:AF)>0,B86=""),1,0) -> 0
A87: =IF(AG87=1,"X","") | B87: 0 | D87: • | E87: Other not covered by above - (state below) | AB87: This line will NOT show on the report | AD87: Always Hide
A88: =IF(AG88=1,"X","") | B88: 1 | D88: • | E88: Leaks from the ensuite. Plumber to inspect and repair. Main bathroom has caused staining to the ceiling below. | AB88: ← Enter Visibility & Data | AD88: Determined by surveyor | AF88: =IF(B88<>"",1,0) -> 1 | AG88: =IF(AND(SUM(AF:AF)>0,OR(AND(B88=1,E88=""),AND(B88="",E88=""),AND(B88="",E88<>""),AND(B88=0,E88<>""))),1,0) -> 0
A89: =IF(AG89=1,"X","") | B89: 1 | D89: • | E89: Lack of ventilation and air movement with the property have caused elevated humidity levels within the building. | AB89: ← Enter Visibility & Data | AD89: Determined by surveyor | AF89: =IF(B89<>"",1,0) -> 1 | AG89: =IF(AND(SUM(AF:AF)>0,OR(AND(B89=1,E89=""),AND(B89="",E89=""),AND(B89="",E89<>""),AND(B89=0,E89<>""))),1,0) -> 0
A90: =IF(AG90=1,"X","") | B90: 1 | D90: • | E90: It is our opinion that the current extraction and ventilation at the property does not provide sufficient ventilation | AB90: ← Enter Visibility & Data | AD90: Determined by surveyor | AF90: =IF(B90<>"",1,0) -> 1 | AG90: =IF(AND(SUM(AF:AF)>0,OR(AND(B90=1,E90=""),AND(B90="",E90=""),AND(B90="",E90<>""),AND(B90=0,E90<>""))),1,0) -> 0
A91: =IF(AG91=1,"X","") | B91: 0 | D91: Airbricks | AB91: ← Enter Visibility | AD91: Determined by surveyor | AF91: =IF(B91<>"",1,0) -> 1 | AG91: =IF(AND(SUM(AF:AF)>0,B91=""),1,0) -> 0
A92: =IF(AG92=1,"X","") | B92: 0 | D92: There were no airbricks installed. | AB92: ← Enter Visibility | AD92: Determined by surveyor | AF92: =IF(B92<>"",1,0) -> 1 | AG92: =IF(AND(SUM(AF:AF)>0,B92=""),1,0) -> 0
A93: =IF(AG93=1,"X","") | B93: 0 | D93: It was not possible to inspect the airbricks due to the following: | AB93: ← Enter Visibility | AD93: Determined by surveyor | AF93: =IF(B93<>"",1,0) -> 1 | AG93: =IF(AND(SUM(AF:AF)>0,B93=""),1,0) -> 0
A94: =IF(AG94=1,"X","") | B94: 0 | D94: • | E94: State below - ensure that images are taken of the obstructions to be added to the report. | AB94: This line will NOT show on the report | AD94: Always Hide
A95: =IF(AG95=1,"X","") | B95: 0 | D95: • | AB95: ← Enter Visibility & Data | AD95: Determined by surveyor | AF95: =IF(B95<>"",1,0) -> 1 | AG95: =IF(AND(SUM(AF:AF)>0,OR(AND(B95=1,E95=""),AND(B95="",E95=""),AND(B95="",E95<>""),AND(B95=0,E95<>""))),1,0) -> 0
A96: =IF(AG96=1,"X","") | B96: 0 | D96: • | AB96: ← Enter Visibility & Data | AD96: Determined by surveyor | AF96: =IF(B96<>"",1,0) -> 1 | AG96: =IF(AND(SUM(AF:AF)>0,OR(AND(B96=1,E96=""),AND(B96="",E96=""),AND(B96="",E96<>""),AND(B96=0,E96<>""))),1,0) -> 0
A97: =IF(AG97=1,"X","") | B97: 0 | D97: • | AB97: ← Enter Visibility & Data | AD97: Determined by surveyor | AF97: =IF(B97<>"",1,0) -> 1 | AG97: =IF(AND(SUM(AF:AF)>0,OR(AND(B97=1,E97=""),AND(B97="",E97=""),AND(B97="",E97<>""),AND(B97=0,E97<>""))),1,0) -> 0
A98: =IF(AG98=1,"X","") | B98: 0 | D98: Use the alt key and the mouse to 'snap' the image to the top and bottom of the cell for alignment. | AB98: This line will NOT show on the report | AD98: Always Hide
B99: 0 | D99: ↓ Image Section 1 ↓ | AB99: This line will NOT show on the report | AD99: Always Hide
A100: =IF(AG100=1,"X","") | B100: =IF(OR(D101="Show",Q101="Show"),1,0) -> 1 | AD100: Always show
A101: =IF(AG101=1,"X","") | B101: 0 | D101: Show | Q101: Show | AB101: ← Enter Image Visibility | AD101: Determined by surveyor | AF101: =IF(OR(D101="Show",D101="",Q101="Show",Q101=""),1,0) -> 1 | AG101: =IF(AND(SUM(AF:AF)>0,OR(D101="",Q101="")),1,0) -> 0
...

Sheet Costing
B1: Sheet Validation | E1: =IF(SUM(AT:AT)=0,"SHEET NOT YET STARTED",IF(SUM(AU:AU)>0,"SHEET NOT COMPLETE","SHEET COMPLETE")) -> SHEET COMPLETE | AS1: Sheet Validation to right | AT1: Check if any data is entered | AU1: Check if field needs to be completed
A3: =IF(AU3=1,"X","") | B3: Enquiry Details
A4: =IF(AU4=1,"X","") | B4: Enquiry number | E4: =IF([1]Details!$C$4=0,"",UPPER([1]Details!$C$4)) -> PRONE455DN | AT4: =IF(E4<>"",1,0) -> 1 | AU4: =IF(AND(SUM(AT:AT)>0,E4=""),1,0) -> 0
A5: =IF(AU5=1,"X","")
A6: =IF(AU6=1,"X","") | B6: Site Details
A7: =IF(AU7=1,"X","") | B7: =[1]Details!$B$7 -> Client Name | E7: =IF([1]Details!$C$7=0,"",PROPER([1]Details!$C$7)) -> Finest Properties | AT7: =IF(E7<>"",1,0) -> 1 | AU7: =IF(AND(SUM(AT:AT)>0,E7=""),1,0) -> 0
A8: =IF(AU8=1,"X","") | B8: =[1]Details!$B$8 -> First Line of site address | E8: =IF([1]Details!$C$8=0,"",PROPER([1]Details!$C$8)) -> Clive House | AT8: =IF(E8<>"",1,0) -> 1 | AU8: =IF(AND(SUM(AT:AT)>0,E8=""),1,0) -> 0
A9: =IF(AU9=1,"X","") | B9: =[1]Details!$B$9 -> Town / City | E9: =IF([1]Details!$C$9=0,"",PROPER([1]Details!$C$9)) -> Appletree Lane | AT9: =IF(E9<>"",1,0) -> 1 | AU9: =IF(AND(SUM(AT:AT)>0,E9=""),1,0) -> 0
A10: =IF(AU10=1,"X","") | B10: =[1]Details!$B$10 -> County | E10: =IF([1]Details!$C$10=0,"",PROPER([1]Details!$C$10)) -> Corbridge | AT10: =IF(E10<>"",1,0) -> 1 | AU10: =IF(AND(SUM(AT:AT)>0,E10=""),1,0) -> 0
A11: =IF(AU11=1,"X","") | B11: =[1]Details!$B$11 -> Site Post Code | E11: =IF([1]Details!$C$11=0,"",UPPER([1]Details!$C$11)) -> NE45 5DN | AT11: =IF(E11<>"",1,0) -> 1 | AU11: =IF(AND(SUM(AT:AT)>0,E11=""),1,0) -> 0
A12: =IF(AU12=1,"X","")
A13: =IF(AU13=1,"X","") | B13: Survey Carried Out By
A14: =IF(AU14=1,"X","") | B14: Surveyor | E14: =IF([1]Details!$C$16=0,"",[1]Details!$C$16) -> Steven Robinson | AT14: =IF(E14<>"",1,0) -> 1 | AU14: =IF(AND(SUM(AT:AT)>0,E14=""),1,0) -> 0
A15: =IF(AU15=1,"X","")
A16: =IF(AU16=1,"X","") | B16: CONDENSATION SHEET
A17: =IF(AU17=1,"X","") | B17: Materials | F17: Area/No. | G17: UOM | H17: Default Mats Cost | I17: Adjusted Mats Cost | J17: M/U | K17: Mats Tot | M17: Labour | N17: Hour Mult | O17: Total Hours | P17: Default Lab Cost | Q17: Adjusted Lab Cost | R17: LMU | S17: Lab Total | T17: Line total | U17: Contractor Materials | V17: Contractor hours pay
A18: =IF(AU18=1,"X","")
A20: =IF(AU20=1,"X","") | B20: PIV - LOFT UNIT | M20: =B20 -> PIV - LOFT UNIT | U20: =B20 -> PIV - LOFT UNIT
A21: =IF(AU21=1,"X","") | B21: VA Pozidry loft unit - heated | F21: 1 | G21: Each | H21: 324.13 | I21: =(H21/100)*(100+$F$25) -> 307.9235 | J21: 0.4 | K21: =F21*I21*(1+J21) -> 431.0929 | M21: =B21 -> VA Pozidry loft unit - heated | N21: 2.5 | O21: =F21*N21 -> 2.5 | P21: =$D$107 -> 30.63 | Q21: =(P21/100)*(100+$F$25) -> 29.0985 | R21: 4 | S21: =(O21*Q21*(1+R21)) -> 363.73125 | T21: =K21+S21 -> 794.82415 | U21: =F21*H21*1.1 -> 356.543 | V21: =O21*$E$107 -> 70 | AT21: =IF(F21<>"",1,0) -> 1 | AU21: =IF(AND(SUM(AT:AT)>0,F21=""),1,0) -> 0
A22: =IF(AU22=1,"X","") | B22: VA Pozidry loft unit - unheated | F22: 0 | G22: Each | H22: 309.96 | I22: =(H22/100)*(100+$F$25) -> 294.462 | J22: 0.4 | K22: =F22*I22*(1+J22) -> 0 | M22: =B22 -> VA Pozidry loft unit - unheated | N22: 2.5 | O22: =F22*N22 -> 0 | P22: =$D$107 -> 30.63 | Q22: =(P22/100)*(100+$F$25) -> 29.0985 | R22: 4 | S22: =(O22*Q22*(1+R22)) -> 0 | T22: =K22+S22 -> 0 | U22: =F22*H22*1.1 -> 0 | V22: =O22*$E$107 -> 0 | AT22: =IF(F22<>"",1,0) -> 1 | AU22: =IF(AND(SUM(AT:AT)>0,F22=""),1,0) -> 0
A23: =IF(AU23=1,"X","") | B23: Electrical Pack - fused spur, cable, JB | F23: 0 | G23: Each | H23: 12.46 | I23: =(H23/100)*(100+$F$25) -> 11.837 | J23: 0.3 | K23: =F23*I23*(1+J23) -> 0 | L23: 0.25 | M23: =B23 -> Electrical Pack - fused spur, cable, JB | N23: 1.5 | O23: =F23*N23 -> 0 | P23: =$D$107 -> 30.63 | Q23: =(P23/100)*(100+$F$25) -> 29.0985 | R23: 1 | S23: =(O23*Q23*(1+R23)) -> 0 | T23: =K23+S23 -> 0 | U23: =F23*H23*1.1 -> 0 | V23: =O23*$E$107 -> 0 | AT23: =IF(F23<>"",1,0) -> 1 | AU23: =IF(AND(SUM(AT:AT)>0,F23=""),1,0) -> 0
A24: =IF(AU24=1,"X","") | B24: Sarkvents | F24: 0 | G24: Each | H24: 3 | I24: =(H24/100)*(100+$F$25) -> 2.85 | J24: 0.3 | K24: =F24*I24*(1+J24) -> 0 | L24: 0.25 | M24: =B24 -> Sarkvents | N24: 0.08 | O24: =F24*N24 -> 0 | P24: =$D$107 -> 30.63 | Q24: =(P24/100)*(100+$F$25) -> 29.0985 | R24: 1 | S24: =(O24*Q24*(1+R24)) -> 0 | T24: =K24+S24 -> 0 | U24: =F24*H24*1.1 -> 0 | V24: =O24*$E$107 -> 0 | AT24: =IF(F24<>"",1,0) -> 1 | AU24: =IF(AND(SUM(AT:AT)>0,F24=""),1,0) -> 0
A25: =IF(AU25=1,"X","") | B25: Section Price Adjustment % | F25: -5 | J25: Totals | K25: =SUM(K21:K24) -> 431.0929 | M25: Totals | O25: =SUM(O21:O24) -> 2.5 | S25: =SUM(S21:S24) -> 363.73125 | T25: =SUM(T21:T24) -> 794.82415 | U25: =SUM(U21:U24) -> 356.543 | V25: =SUM(V21:V24) -> 70
A27: =IF(AU27=1,"X","") | B27: PIV - WALL MOUNTED UNIT | M27: =B27 -> PIV - WALL MOUNTED UNIT | U27: =B27 -> PIV - WALL MOUNTED UNIT
A28: =IF(AU28=1,"X","") | B28: VA Pozidry Compact wall mounted unit | F28: 0 | G28: Each | H28: 273.74 | I28: =(H28/100)*(100+$F$42) -> 273.74 | J28: 0.4 | K28: =F28*I28*(1+J28) -> 0 | L28: 0.75 | M28: =B28 -> VA Pozidry Compact wall mounted unit | N28: 4 | O28: =F28*N28 -> 0 | P28: =$D$107 -> 30.63 | Q28: =(P28/100)*(100+$F$42) -> 30.63 | R28: 3 | S28: =(O28*Q28*(1+R28)) -> 0 | T28: =K28+S28 -> 0 | U28: =F28*H28*1.1 -> 0 | V28: =O28*$E$107 -> 0 | AT28: =IF(F28<>"",1,0) -> 1 | AU28: =IF(AND(SUM(AT:AT)>0,F28=""),1,0) -> 0
A29: =IF(AU29=1,"X","") | B29: Electrical Pack - fused spur, cable, JB | F29: 0 | G29: Each | H29: 12.46 | I29: =(H29/100)*(100+$F$42) -> 12.46 | J29: 0.3 | K29: =F29*I29*(1+J29) -> 0 | L29: 0.25 | M29: =B29 -> Electrical Pack - fused spur, cable, JB | N29: 1.5 | O29: =F29*N29 -> 0 | P29: =$D$107 -> 30.63 | Q29: =(P29/100)*(100+$F$42) -> 30.63 | R29: 1 | S29: =(O29*Q29*(1+R29)) -> 0 | T29: =K29+S29 -> 0 | U29: =F29*H29*1.1 -> 0 | V29: =O29*$E$107 -> 0 | AT29: =IF(F29<>"",1,0) -> 1 | AU29: =IF(AND(SUM(AT:AT)>0,F29=""),1,0) -> 0
A30: =IF(AU30=1,"X","") | B30: Ducting - 1m length | F30: 0 | G30: Each | H30: 3.85 | I30: =(H30/100)*(100+$F$42) -> 3.85 | J30: 0.3 | K30: =F30*I30*(1+J30) -> 0 | L30: 0.25 | M30: =B30 -> Ducting - 1m length | N30: 0.1 | O30: =F30*N30 -> 0 | P30: =$D$107 -> 30.63 | Q30: =(P30/100)*(100+$F$42) -> 30.63 | R30: 1 | S30: =(O30*Q30*(1+R30)) -> 0 | T30: =K30+S30 -> 0 | U30: =F30*H30*1.1 -> 0 | V30: =O30*$E$107 -> 0 | AT30: =IF(F30<>"",1,0) -> 1 | AU30: =IF(AND(SUM(AT:AT)>0,F30=""),1,0) -> 0
A31: =IF(AU31=1,"X","") | B31: Ducting - round elbow | F31: 0 | G31: Each | H31: 2.78 | I31: =(H31/100)*(100+$F$42) -> 2.78 | J31: 0.3 | K31: =F31*I31*(1+J31) -> 0 | L31: 0.25 | M31: =B31 -> Ducting - round elbow | N31: 0.1 | O31: =F31*N31 -> 0 | P31: =$D$107 -> 30.63 | Q31: =(P31/100)*(100+$F$42) -> 30.63 | R31: 1 | S31: =(O31*Q31*(1+R31)) -> 0 | T31: =K31+S31 -> 0 | U31: =F31*H31*1.1 -> 0 | V31: =O31*$E$107 -> 0 | AT31: =IF(F31<>"",1,0) -> 1 | AU31: =IF(AND(SUM(AT:AT)>0,F31=""),1,0) -> 0
A32: =IF(AU32=1,"X","") | B32: Ducting - round - straight conn | F32: 0 | G32: Each | H32: 0.52 | I32: =(H32/100)*(100+$F$42) -> 0.52 | J32: 0.3 | K32: =F32*I32*(1+J32) -> 0 | L32: 0.25 | M32: =B32 -> Ducting - round - straight conn | N32: 0.1 | O32: =F32*N32 -> 0 | P32: =$D$107 -> 30.63 | Q32: =(P32/100)*(100+$F$42) -> 30.63 | R32: 1 | S32: =(O32*Q32*(1+R32)) -> 0 | T32: =K32+S32 -> 0 | U32: =F32*H32*1.1 -> 0 | V32: =O32*$E$107 -> 0 | AT32: =IF(F32<>"",1,0) -> 1 | AU32: =IF(AND(SUM(AT:AT)>0,F32=""),1,0) -> 0
A33: =IF(AU33=1,"X","") | B33: Ducting - round 1m | F33: 0 | G33: Each | H33: 3.85 | I33: =(H33/100)*(100+$F$42) -> 3.85 | J33: 0.3 | K33: =F33*I33*(1+J33) -> 0 | L33: 0.25 | M33: =B33 -> Ducting - round 1m | N33: 0.1 | O33: =F33*N33 -> 0 | P33: =$D$107 -> 30.63 | Q33: =(P33/100)*(100+$F$42) -> 30.63 | R33: 1 | S33: =(O33*Q33*(1+R33)) -> 0 | T33: =K33+S33 -> 0 | U33: =F33*H33*1.1 -> 0 | V33: =O33*$E$107 -> 0 | AT33: =IF(F33<>"",1,0) -> 1 | AU33: =IF(AND(SUM(AT:AT)>0,F33=""),1,0) -> 0
A34: =IF(AU34=1,"X","") | B34: Ducting - flat to round adaptor | F34: 0 | G34: Each | H34: 1.63 | I34: =(H34/100)*(100+$F$42) -> 1.63 | J34: 0.3 | K34: =F34*I34*(1+J34) -> 0 | L34: 0.25 | M34: =B34 -> Ducting - flat to round adaptor | N34: 0.1 | O34: =F34*N34 -> 0 | P34: =$D$107 -> 30.63 | Q34: =(P34/100)*(100+$F$42) -> 30.63 | R34: 1 | S34: =(O34*Q34*(1+R34)) -> 0 | T34: =K34+S34 -> 0 | U34: =F34*H34*1.1 -> 0 | V34: =O34*$E$107 -> 0 | AT34: =IF(F34<>"",1,0) -> 1 | AU34: =IF(AND(SUM(AT:AT)>0,F34=""),1,0) -> 0
A35: =IF(AU35=1,"X","") | B35: Ducting - flat straight connector | F35: 0 | G35: Each | H35: 1.14 | I35: =(H35/100)*(100+$F$42) -> 1.14 | J35: 0.3 | K35: =F35*I35*(1+J35) -> 0 | L35: 0.25 | M35: =B35 -> Ducting - flat straight connector | N35: 0.1 | O35: =F35*N35 -> 0 | P35: =$D$107 -> 30.63 | Q35: =(P35/100)*(100+$F$42) -> 30.63 | R35: 1 | S35: =(O35*Q35*(1+R35)) -> 0 | T35: =K35+S35 -> 0 | U35: =F35*H35*1.1 -> 0 | V35: =O35*$E$107 -> 0 | AT35: =IF(F35<>"",1,0) -> 1 | AU35: =IF(AND(SUM(AT:AT)>0,F35=""),1,0) -> 0
A36: =IF(AU36=1,"X","") | B36: Ducting - flat horizontal bend | F36: 0 | G36: Each | H36: 3.01 | I36: =(H36/100)*(100+$F$42) -> 3.01 | J36: 0.3 | K36: =F36*I36*(1+J36) -> 0 | L36: 0.25 | M36: =B36 -> Ducting - flat horizontal bend | N36: 0.1 | O36: =F36*N36 -> 0 | P36: =$D$107 -> 30.63 | Q36: =(P36/100)*(100+$F$42) -> 30.63 | R36: 1 | S36: =(O36*Q36*(1+R36)) -> 0 | T36: =K36+S36 -> 0 | U36: =F36*H36*1.1 -> 0 | V36: =O36*$E$107 -> 0 | AT36: =IF(F36<>"",1,0) -> 1 | AU36: =IF(AND(SUM(AT:AT)>0,F36=""),1,0) -> 0
A37: =IF(AU37=1,"X","") | B37: Ducting - flat vertical bend | F37: 0 | G37: Each | H37: 3.01 | I37: =(H37/100)*(100+$F$42) -> 3.01 | J37: 0.3 | K37: =F37*I37*(1+J37) -> 0 | L37: 0.25 | M37: =B37 -> Ducting - flat vertical bend | N37: 0.1 | O37: =F37*N37 -> 0 | P37: =$D$107 -> 30.63 | Q37: =(P37/100)*(100+$F$42) -> 30.63 | R37: 1 | S37: =(O37*Q37*(1+R37)) -> 0 | T37: =K37+S37 -> 0 | U37: =F37*H37*1.1 -> 0 | V37: =O37*$E$107 -> 0 | AT37: =IF(F37<>"",1,0) -> 1 | AU37: =IF(AND(SUM(AT:AT)>0,F37=""),1,0) -> 0
A38: =IF(AU38=1,"X","") | B38: Ducting - flat - 1m | F38: 0 | G38: Each | H38: 2.87 | I38: =(H38/100)*(100+$F$42) -> 2.87 | J38: 0.3 | K38: =F38*I38*(1+J38) -> 0 | L38: 0.25 | M38: =B38 -> Ducting - flat - 1m | N38: 0.1 | O38: =F38*N38 -> 0 | P38: =$D$107 -> 30.63 | Q38: =(P38/100)*(100+$F$42) -> 30.63 | R38: 1 | S38: =(O38*Q38*(1+R38)) -> 0 | T38: =K38+S38 -> 0 | U38: =F38*H38*1.1 -> 0 | V38: =O38*$E$107 -> 0 | AT38: =IF(F38<>"",1,0) -> 1 | AU38: =IF(AND(SUM(AT:AT)>0,F38=""),1,0) -> 0
A39: =IF(AU39=1,"X","") | B39: Ducting - insulated flexi (3m Length) | F39: 0 | G39: Each | H39: 2.5 | I39: =(H39/100)*(100+$F$42) -> 2.5 | J39: 0.3 | K39: =F39*I39*(1+J39) -> 0 | L39: 0.25 | M39: =B39 -> Ducting - insulated flexi (3m Length) | N39: 0.1 | O39: =F39*N39 -> 0 | P39: =$D$107 -> 30.63 | Q39: =(P39/100)*(100+$F$42) -> 30.63 | R39: 1 | S39: =(O39*Q39*(1+R39)) -> 0 | T39: =K39+S39 -> 0 | U39: =F39*H39*1.1 -> 0 | V39: =O39*$E$107 -> 0 | AT39: =IF(F39<>"",1,0) -> 1 | AU39: =IF(AND(SUM(AT:AT)>0,F39=""),1,0) -> 0
... A41: =IF(AU41=1,"X","") | B41: Diamond core 107mm hole | F41: 0 | G41: Each | H41: 0 | I41: =(H41/100)*(100+$F$42) -> 0 | J41: 0.3 | K41: =F41*I41*(1+J41) -> 0 | L41: 0.25 | M41: =B41 -> Diamond core 107mm hole | N41: 2 | O41: =F41*N41 -> 0 | P41: =$D$107 -> 30.63 | Q41: =(P41/100)*(100+$F$42) -> 30.63 | R41: 1 | S41: =(O41*Q41*(1+R41)) -> 0 | T41: =K41+S41 -> 0 | U41: =F41*H41*1.1 -> 0 | V41: =O41*$E$107 -> 0 | AT41: =IF(F41<>"",1,0) -> 1 | AU41: =IF(AND(SUM(AT:AT)>0,F41=""),1,0) -> 0
A42: =IF(AU42=1,"X","") | B42: Section Price Adjustment % | F42: 0 | J42: Totals | K42: =SUM(K28:K41) -> 0 | M42: Totals | O42: =SUM(O28:O41) -> 0 | S42: =SUM(S28:S41) -> 0 | T42: =SUM(T28:T41) -> 0 | U42: =SUM(U28:U41) -> 0 | V42: =SUM(V28:V41) -> 0
A44: =IF(AU44=1,"X","") | B44: TRICKLE AND BOOST HUMIDISTAT FAN | M44: =B44 -> TRICKLE AND BOOST HUMIDISTAT FAN | U44: =B44 -> TRICKLE AND BOOST HUMIDISTAT FAN
A45: =IF(AU45=1,"X","") | B45: Trickle and boost humidistat fan (greenwood) | F45: 5 | G45: Each | H45: 70.2 | I45: =(H45/100)*(100+$F$49) -> 70.2 | J45: 0.3 | K45: =F45*I45*(1+J45) -> 456.3 | L45: 0.75 | M45: =B45 -> Trickle and boost humidistat fan (greenwood) | N45: 1.5 | O45: =F45*N45 -> 7.5 | P45: =$D$107 -> 30.63 | Q45: =(P45/100)*(100+$F$49) -> 30.63 | R45: 1 | S45: =(O45*Q45*(1+R45)) -> 459.45 | T45: =K45+S45 -> 915.75 | U45: =F45*H45*1.1 -> 386.1 | V45: =O45*$E$107 -> 210 | AT45: =IF(F45<>"",1,0) -> 1 | AU45: =IF(AND(SUM(AT:AT)>0,F45=""),1,0) -> 0
A46: =IF(AU46=1,"X","") | B46: Electrical Pack - fused spur, cable, JB | F46: 0 | G46: Each | H46: 12.46 | I46: =(H46/100)*(100+$F$49) -> 12.46 | J46: 0.3 | K46: =F46*I46*(1+J46) -> 0 | L46: 0.25 | M46: =B46 -> Electrical Pack - fused spur, cable, JB | N46: 1.5 | O46: =F46*N46 -> 0 | P46: =$D$107 -> 30.63 | Q46: =(P46/100)*(100+$F$49) -> 30.63 | R46: 1 | S46: =(O46*Q46*(1+R46)) -> 0 | T46: =K46+S46 -> 0 | U46: =F46*H46*1.1 -> 0 | V46: =O46*$E$107 -> 0 | AT46: =IF(F46<>"",1,0) -> 1 | AU46: =IF(AND(SUM(AT:AT)>0,F46=""),1,0) -> 0
A47: =IF(AU47=1,"X","") | B47: Grille | F47: 0 | G47: Each | H47: 2.42 | I47: =(H47/100)*(100+$F$49) -> 2.42 | J47: 0.3 | K47: =F47*I47*(1+J47) -> 0 | L47: 0.25 | M47: =B47 -> Grille | N47: 0.1 | O47: =F47*N47 -> 0 | P47: =$D$107 -> 30.63 | Q47: =(P47/100)*(100+$F$49) -> 30.63 | R47: 1 | S47: =(O47*Q47*(1+R47)) -> 0 | T47: =K47+S47 -> 0 | U47: =F47*H47*1.1 -> 0 | V47: =O47*$E$107 -> 0 | AT47: =IF(F47<>"",1,0) -> 1 | AU47: =IF(AND(SUM(AT:AT)>0,F47=""),1,0) -> 0
A48: =IF(AU48=1,"X","") | B48: Diamond core 107mm hole | F48: 0 | G48: Each | H48: 0 | I48: =(H48/100)*(100+$F$49) -> 0 | J48: 0.3 | K48: =F48*I48*(1+J48) -> 0 | L48: 0.25 | M48: =B48 -> Diamond core 107mm hole | N48: 2 | O48: =F48*N48 -> 0 | P48: =$D$107 -> 30.63 | Q48: =(P48/100)*(100+$F$49) -> 30.63 | R48: 1 | S48: =(O48*Q48*(1+R48)) -> 0 | T48: =K48+S48 -> 0 | U48: =F48*H48*1.1 -> 0 | V48: =O48*$E$107 -> 0 | AT48: =IF(F48<>"",1,0) -> 1 | AU48: =IF(AND(SUM(AT:AT)>0,F48=""),1,0) -> 0
A49: =IF(AU49=1,"X","") | B49: Section Price Adjustment % | F49: 0 | J49: Totals | K49: =SUM(K45:K48) -> 456.3 | M49: Totals | O49: =SUM(O45:O48) -> 7.5 | S49: =SUM(S45:S48) -> 459.45 | T49: =SUM(T45:T48) -> 915.75 | U49: =SUM(U45:U48) -> 386.1 | V49: =SUM(V45:V48) -> 210
A51: =IF(AU51=1,"X","") | B51: DRYAIRE CPASS (PLASMO) INSULATED PULLCORD PASSIVE VENT | M51: =B51 -> DRYAIRE CPASS (PLASMO) INSULATED PULLCORD PASSIVE VENT | U51: =B51 -> DRYAIRE CPASS (PLASMO) INSULATED PULLCORD PASSIVE VENT
A52: =IF(AU52=1,"X","") | B52: Dryaire Cpass (plasmo) insulated pullcord passive vent | F52: 0 | G52: Each | H52: 36.18 | I52: =(H52/100)*(100+$F$54) -> 36.18 | J52: 0.3 | K52: =F52*I52*(1+J52) -> 0 | L52: 0.75 | M52: =B52 -> Dryaire Cpass (plasmo) insulated pullcord passive vent | N52: 1.5 | O52: =F52*N52 -> 0 | P52: =$D$107 -> 30.63 | Q52: =(P52/100)*(100+$F$54) -> 30.63 | R52: 1 | S52: =(O52*Q52*(1+R52)) -> 0 | T52: =K52+S52 -> 0 | U52: =F52*H52*1.1 -> 0 | V52: =O52*$E$107 -> 0 | AT52: =IF(F52<>"",1,0) -> 1 | AU52: =IF(AND(SUM(AT:AT)>0,F52=""),1,0) -> 0
A53: =IF(AU53=1,"X","") | B53: Diamond core 107mm hole | F53: 0 | G53: Each | H53: 0 | I53: =(H53/100)*(100+$F$54) -> 0 | J53: 0.3 | K53: =F53*I53*(1+J53) -> 0 | L53: 0.25 | M53: =B53 -> Diamond core 107mm hole | N53: 2 | O53: =F53*N53 -> 0 | P53: =$D$107 -> 30.63 | Q53: =(P53/100)*(100+$F$54) -> 30.63 | R53: 1 | S53: =(O53*Q53*(1+R53)) -> 0 | T53: =K53+S53 -> 0 | U53: =F53*H53*1.1 -> 0 | V53: =O53*$E$107 -> 0 | AT53: =IF(F53<>"",1,0) -> 1 | AU53: =IF(AND(SUM(AT:AT)>0,F53=""),1,0) -> 0
A54: =IF(AU54=1,"X","") | B54: Section Price Adjustment % | F54: 0 | J54: Totals | K54: =SUM(K52:K53) -> 0 | M54: Totals | O54: =SUM(O52:O53) -> 0 | S54: =SUM(S52:S53) -> 0 | T54: =SUM(T52:T53) -> 0 | U54: =SUM(U52:U53) -> 0 | V54: =SUM(V52:V53) -> 0
A56: =IF(AU56=1,"X","") | B56: Dryaire Cvent | M56: =B56 -> Dryaire Cvent | U56: =B56 -> Dryaire Cvent
A57: =IF(AU57=1,"X","") | B57: Dryaire Cvent | F57: 0 | G57: Each | H57: 12.5 | I57: =(H57/100)*(100+$F$59) -> 12.5 | J57: 0.3 | K57: =F57*I57*(1+J57) -> 0 | L57: 0.75 | M57: =B57 -> Dryaire Cvent | N57: 1.5 | O57: =F57*N57 -> 0 | P57: =$D$107 -> 30.63 | Q57: =(P57/100)*(100+$F$59) -> 30.63 | R57: 1 | S57: =(O57*Q57*(1+R57)) -> 0 | T57: =K57+S57 -> 0 | U57: =F57*H57*1.1 -> 0 | V57: =O57*$E$107 -> 0 | AT57: =IF(F57<>"",1,0) -> 1 | AU57: =IF(AND(SUM(AT:AT)>0,F57=""),1,0) -> 0
A58: =IF(AU58=1,"X","") | B58: Diamond core 107mm hole | F58: 0 | G58: Each | H58: 0 | I58: =(H58/100)*(100+$F$59) -> 0 | J58: 0.3 | K58: =F58*I58*(1+J58) -> 0 | L58: 0.25 | M58: =B58 -> Diamond core 107mm hole | N58: 2 | O58: =F58*N58 -> 0 | P58: =$D$107 -> 30.63 | Q58: =(P58/100)*(100+$F$59) -> 30.63 | R58: 1 | S58: =(O58*Q58*(1+R58)) -> 0 | T58: =K58+S58 -> 0 | U58: =F58*H58*1.1 -> 0 | V58: =O58*$E$107 -> 0 | AT58: =IF(F58<>"",1,0) -> 1 | AU58: =IF(AND(SUM(AT:AT)>0,F58=""),1,0) -> 0
A59: =IF(AU59=1,"X","") | B59: Section Price Adjustment % | F59: 0 | J59: Totals | K59: =SUM(K57:K58) -> 0 | M59: Totals | O59: =SUM(O57:O58) -> 0 | S59: =SUM(S57:S58) -> 0 | T59: =SUM(T57:T58) -> 0 | U59: =SUM(U57:U58) -> 0 | V59: =SUM(V57:V58) -> 0
A61: =IF(AU61=1,"X","") | B61: Joinery: Supply and fit boxwork for ducting | M61: =B61 -> Joinery: Supply and fit boxwork for ducting | U61: =B61 -> Joinery: Supply and fit boxwork for ducting
A62: =IF(AU62=1,"X","") | B62: Joinery to box in ducting (per metre) Min charge 2.4 metres | F62: 0 | G62: LM | H62: =IF(F62=0,0,IF(F62<2.4,(15*2.4)/F62,15)) -> 0 | I62: =(H62/100)*(100+$F$63) -> 0 | J62: 0.3 | K62: =F62*I62*(1+J62) -> 0 | M62: =B62 -> Joinery to box in ducting (per metre) Min charge 2.4 metres | N62: 0.5 | O62: =IF(F62=0,0,IF(F62=0,0,IF(F62<2.4,(N62*2.4),(N62*F62)))) -> 0 | P62: =$D$107 -> 30.63 | Q62: =(P62/100)*(100+$F$63) -> 30.63 | R62: 1 | S62: =(O62*Q62*(1+R62)) -> 0 | T62: =K62+S62 -> 0 | U62: =F62*H62*1.1 -> 0 | V62: =O62*$E$107 -> 0 | W62: Optional Item For Customer | AT62: =IF(F62<>"",1,0) -> 1 | AU62: =IF(AND(SUM(AT:AT)>0,F62=""),1,0) -> 0
A63: =IF(AU63=1,"X","") | B63: Section Price Adjustment % | F63: 0 | J63: Totals | K63: =SUM(K62:K62) -> 0 | M63: Totals | O63: =SUM(O62:O62) -> 0 | S63: =SUM(S62:S62) -> 0 | T63: =SUM(T62:T62) -> 0 | U63: =SUM(U62:U62) -> 0 | V63: =SUM(V62:V62) -> 0
A65: =IF(AU65=1,"X","") | B65: Loft hatch - new hatchwith sturdy fold down ladder with handrail and switched lamp | M65: =B65 -> Loft hatch - new hatchwith sturdy fold down ladder with handrail and switched lamp | U65: =B65 -> Loft hatch - new hatchwith sturdy fold down ladder with handrail and switched lamp
A66: =IF(AU66=1,"X","") | B66: New loft hatch - with sturdy fold down ladder with handrail and switched lamp | F66: 0 | G66: Each | H66: 360 | I66: =(H66/100)*(100+$F$67) -> 360 | J66: 0.3 | K66: =F66*I66*(1+J66) -> 0 | M66: =B66 -> New loft hatch - with sturdy fold down ladder with handrail and switched lamp | N66: 4 | O66: =F66*N66 -> 0 | P66: =$D$107 -> 30.63 | Q66: =(P66/100)*(100+$F$67) -> 30.63 | R66: 1 | S66: =(O66*Q66*(1+R66)) -> 0 | T66: =K66+S66 -> 0 | U66: =F66*H66*1.1 -> 0 | V66: =O66*$E$107 -> 0 | W66: Optional Item For Customer | AT66: =IF(F66<>"",1,0) -> 1 | AU66: =IF(AND(SUM(AT:AT)>0,F66=""),1,0) -> 0
A67: =IF(AU67=1,"X","") | B67: Section Price Adjustment % | F67: 0 | J67: Totals | K67: =SUM(K66:K66) -> 0 | M67: Totals | O67: =SUM(O65:O66) -> 0 | S67: =SUM(S66:S66) -> 0 | T67: =SUM(T66:T66) -> 0 | U67: =SUM(U66:U66) -> 0 | V67: =SUM(V66:V66) -> 0
A69: =IF(AU69=1,"X","") | B69: Loft Hatch - enlarge current loft hatch | M69: =B69 -> Loft Hatch - enlarge current loft hatch | U69: =B69 -> Loft Hatch - enlarge current loft hatch
A70: =IF(AU70=1,"X","") | B70: Existing loft hatch - enlarge loft hatch | F70: 0 | G70: Each | H70: 45 | I70: =(H70/100)*(100+$F$71) -> 45 | J70: 0.3 | K70: =F70*I70*(1+J70) -> 0 | M70: =B70 -> Existing loft hatch - enlarge loft hatch | N70: 4 | O70: =F70*N70 -> 0 | P70: =$D$107 -> 30.63 | Q70: =(P70/100)*(100+$F$71) -> 30.63 | R70: 1 | S70: =(O70*Q70*(1+R70)) -> 0 | T70: =K70+S70 -> 0 | U70: =F70*H70*1.1 -> 0 | V70: =O70*$E$107 -> 0 | W70: Optional Item For Customer | AT70: =IF(F70<>"",1,0) -> 1 | AU70: =IF(AND(SUM(AT:AT)>0,F70=""),1,0) -> 0
A71: =IF(AU71=1,"X","") | B71: Section Price Adjustment % | F71: 0 | J71: Totals | K71: =SUM(K70:K70) -> 0 | M71: Totals | O71: =SUM(O69:O70) -> 0 | S71: =SUM(S70:S70) -> 0 | T71: =SUM(T70:T70) -> 0 | U71: =SUM(U70:U70) -> 0 | V71: =SUM(V70:V70) -> 0
A73: =IF(AU73=1,"X","") | B73: Mould Treatments | M73: =B73 -> Mould Treatments | U73: =B73 -> Mould Treatments
A74: =IF(AU74=1,"X","") | B74: Mould treatment | F74: 6 | G74: M2 | H74: 0.5 | I74: =(H74/100)*(100+$F$75) -> 0.5 | J74: 0.3 | K74: =F74*I74*(1+J74) -> 3.9 | M74: =B74 -> Mould treatment | N74: 0.25 | O74: =F74*N74 -> 1.5 | P74: =$D$107 -> 30.63 | Q74: =(P74/100)*(100+$F$75) -> 30.63 | R74: 1 | S74: =(O74*Q74*(1+R74)) -> 91.89 | T74: =K74+S74 -> 95.79 | U74: =F74*H74*1.1 -> 3.3 | V74: =O74*$E$107 -> 42 | W74: Optional Item For Customer | AT74: =IF(F74<>"",1,0) -> 1 | AU74: =IF(AND(SUM(AT:AT)>0,F74=""),1,0) -> 0
A75: =IF(AU75=1,"X","") | B75: Section Price Adjustment % | F75: 0 | J75: Totals | K75: =SUM(K74:K74) -> 3.9 | M75: Totals | O75: =SUM(O73:O74) -> 1.5 | S75: =SUM(S74:S74) -> 91.89 | T75: =SUM(T74:T74) -> 95.79 | U75: =SUM(U74:U74) -> 3.3 | V75: =SUM(V74:V74) -> 42
A77: =IF(AU77=1,"X","") | B77: Asbestos Testing | M77: =B77 -> Asbestos Testing | U77: =B77 -> Asbestos Testing
A78: =IF(AU78=1,"X","") | B78: Asbestos Testing | F78: 0 | G78: Each | H78: 30 | I78: =(H78/100)*(100+$F$79) -> 30 | J78: 0.3 | K78: =F78*I78*(1+J78) -> 0 | M78: =B78 -> Asbestos Testing | N78: 0.64 | O78: =F78*N78 -> 0 | P78: =$D$107 -> 30.63 | Q78: =(P78/100)*(100+$F$79) -> 30.63 | R78: 1 | S78: =(O78*Q78*(1+R78)) -> 0 | T78: =K78+S78 -> 0 | U78: =F78*H78*1.1 -> 0 | V78: =O78*$E$107 -> 0 | W78: Optional Item For Customer | AT78: =IF(F78<>"",1,0) -> 1 | AU78: =IF(AND(SUM(AT:AT)>0,F78=""),1,0) -> 0
A79: =IF(AU79=1,"X","") | B79: Section Price Adjustment % | F79: 0 | J79: Totals | K79: =SUM(K78:K78) -> 0 | M79: Totals | O79: =SUM(O77:O78) -> 0 | S79: =SUM(S78:S78) -> 0 | T79: =SUM(T78:T78) -> 0 | U79: =SUM(U78:U78) -> 0 | V79: =SUM(V78:V78) -> 0
A81: =IF(AU81=1,"X","") | B81: Airbricks | M81: =B81 -> Airbricks | U81: =B81 -> Airbricks
A82: =IF(AU82=1,"X","") | B82: Clean out airbrick/fit new face | F82: 0 | G82: Each | H82: 16 | I82: =(H82/100)*(100+$F$85) -> 16 | J82: 0.3 | K82: =F82*I82*(1+J82) -> 0 | M82: =B82 -> Clean out airbrick/fit new face | N82: 0.5 | O82: =F82*N82 -> 0 | P82: =$D$107 -> 30.63 | Q82: =(P82/100)*(100+$F$85) -> 30.63 | R82: 1 | S82: =(O82*Q82*(1+R82)) -> 0 | T82: =K82+S82 -> 0 | U82: =F82*H82*1.1 -> 0 | V82: =O82*$E$107 -> 0 | AT82: =IF(F82<>"",1,0) -> 1 | AU82: =IF(AND(SUM(AT:AT)>0,F82=""),1,0) -> 0
A83: =IF(AU83=1,"X","") | B83: Lift/upgrade existing airbrick/fit new face | F83: 0 | G83: Each | H83: 16 | I83: =(H83/100)*(100+$F$85) -> 16 | J83: 0.3 | K83: =F83*I83*(1+J83) -> 0 | M83: =B83 -> Lift/upgrade existing airbrick/fit new face | N83: 0.8 | O83: =F83*N83 -> 0 | P83: =$D$107 -> 30.63 | Q83: =(P83/100)*(100+$F$85) -> 30.63 | R83: 1 | S83: =(O83*Q83*(1+R83)) -> 0 | T83: =K83+S83 -> 0 | U83: =F83*H83*1.1 -> 0 | V83: =O83*$E$107 -> 0 | AT83: =IF(F83<>"",1,0) -> 1 | AU83: =IF(AND(SUM(AT:AT)>0,F83=""),1,0) -> 0
A84: =IF(AU84=1,"X","") | B84: Install additional airbrick | F84: 0 | G84: Each | H84: 16 | I84: =(H84/100)*(100+$F$85) -> 16 | J84: 0.3 | K84: =F84*I84*(1+J84) -> 0 | M84: =B84 -> Install additional airbrick | N84: 2 | O84: =F84*N84 -> 0 | P84: =$D$107 -> 30.63 | Q84: =(P84/100)*(100+$F$85) -> 30.63 | R84: 1 | S84: =(O84*Q84*(1+R84)) -> 0 | T84: =K84+S84 -> 0 | U84: =F84*H84*1.1 -> 0 | V84: =O84*$E$107 -> 0 | AT84: =IF(F84<>"",1,0) -> 1 | AU84: =IF(AND(SUM(AT:AT)>0,F84=""),1,0) -> 0
A85: =IF(AU85=1,"X","") | B85: Section Price Adjustment % | F85: 0 | J85: Totals | K85: =SUM(K82:K84) -> 0 | M85: Totals | O85: =SUM(O82:O84) -> 0 | S85: =SUM(S82:S84) -> 0 | T85: =SUM(T82:T84) -> 0 | U85: =SUM(U82:U84) -> 0 | V85: =SUM(V82:V84) -> 0
A87: =IF(AU87=1,"X","") | B87: Skip hire 8yd | M87: =B87 -> Skip hire 8yd | U87: =B87 -> Skip hire 8yd
A88: =IF(AU88=1,"X","") | B88: Rubbish removal skips | F88: 0 | G88: Each | H88: 270 | I88: =H88 -> 270 | J88: 0.3 | K88: =F88*I88*(1+J88) -> 0 | M88: =B88 -> Rubbish removal skips | N88: 0 | O88: 0 | P88: =$D$107 -> 30.63 | Q88: =P88 -> 30.63 | R88: 1 | S88: =(O88*Q88*(1+R88)) -> 0 | T88: =K88+S88 -> 0 | U88: 0 | V88: 0 | AT88: =IF(F88<>"",1,0) -> 1 | AU88: =IF(AND(SUM(AT:AT)>0,F88=""),1,0) -> 0
A90: =IF(AU90=1,"X","")
A91: =IF(AU91=1,"X","") | E91: Materials sub tot | K91: =K25+K42+K49+K54+K59+K63+K67+K71+K75+K79+K85+K88 -> 891.2929 | M91: TT Totals | U91: Contractor Totals
A92: =IF(AU92=1,"X","") | E92: Labour sub tot | H92: =O92 -> 11.5 | K92: =S25+S42+S49+S54+S59+S63+S67+S71+S75+S79+S85+S88 -> 915.07125 | M92: Labour hours sub total | O92: =O25+O42+O49+O54+O59+O63+O67+O71+O75+O79+O85+O88 -> 11.5 | U92: =U25+U42+U49+U54+U59+U63+U67+U71+U75+U79+U85+U88 -> 745.943 | V92: =V25+V42+V49+V54+V59+V63+V67+V71+V75+V79+V85+V88 -> 322
A93: =IF(AU93=1,"X","") | H93: Travel | K93: =(F107*C107)+((K98*K99)*2)*J107 -> 139.932 | M93: Hours travel | O93: =K98*K99*2*K100/30 -> 3.0666667
A94: =IF(AU94=1,"X","") | H94: Price | K94: =SUM(K91:K93) -> 1946.2962 | M94: Total hours | O94: =SUM(O92:O93) -> 14.566667 | U94: Travel | V94: =K98*(K99*2)*0.45 -> 41.4
A95: =IF(AU95=1,"X","") | H95: Vat | K95: =K94*0.2 -> 389.25923 | U95: Tot | V95: =U92+V92+V94 -> 1109.343
A96: =IF(AU96=1,"X","") | H96: Total price inc vat | K96: =SUM(K94:K95) -> 2335.5554
A97: =IF(AU97=1,"X","") | M97: For Office Only
A98: =IF(AU98=1,"X","") | J98: No of days | K98: =(ROUNDUP((O92/6.5)/K100,0)) -> 2
A99: =IF(AU99=1,"X","") | J99: Distance from office to job (one way) | K99: =IF([1]Details!$C$12=0,"",[1]Details!$C$12) -> 23 | M99: The value of the csv import on upload should match the figures to the right (this may be less than the totals to the left as optional items are are not calculated up on the import until the customer selects them) | S99: Sub Total | U99: =SUMIFS('CF CSV Upload'!P:P,'CF CSV Upload'!L:L,"No",'CF CSV Upload'!Q:Q,"Yes") -> 1946.2962 | AT99: =IF(K99<>"",1,0) -> 1 | AU99: =IF(AND(SUM(AT:AT)>0,K99=""),1,0) -> 0
A100: =IF(AU100=1,"X","") | J100: No of men travelling | K100: 1 | S100: Tax: VAT (20%) | U100: =U99*0.2 -> 389.25923 | AT100: =IF(K100<>"",1,0) -> 1 | AU100: =IF(AND(SUM(AT:AT)>0,K100=""),1,0) -> 0
A101: =IF(AU101=1,"X","") | S101: Total | U101: =U99+U100 -> 2335.5554
A103: =IF(AU103=1,"X","") | B103: Choose Estimate Cover Sheet Image To Use (dropdown) | F103: Image 1: Default or Miscellaneous | M103: View Images (this link will take you to the the Estimates Coversheet Images Tab) | AT103: =IF(F103<>"",1,0) -> 1 | AU103: =IF(AND(SUM(AT:AT)>0,F103=""),1,0) -> 0
B104: Survey sheet end
C105: Base Travel Hourly rate | D105: Base Labour Hourly rate | E105: Contractor Labour Hourly rate | F105: Approx Travel cost
F106: Hours | H106: mens travel | J106: Vehicle cost | K106: Total
C107: =D107 -> 30.63 | D107: 30.63 | E107: 28 | F107: =O93 -> 3.0666667 | H107: =F107*D107 -> 93.932 | J107: 0.5 | K107: =(F107*C107)+(K98*K99*2)*J107 -> 139.932

Sheet Customer Summary
B1: =IF(Costing!E1="SHEET NOT COMPLETE","PLEASE COMPLETE COSTING BEFORE SUPPLYING A PRICE","")
B2: Customer Pricing Summary
B3: # | C3: Area of Works | D3: Optional Item? | E3: Price (Without Optional items) | F3: Price (With Optional Items)
B4: 1 | C4: Condensation control: Supply and install Loft Dryaire system & required accessories | D4: No | E4: =IF(D4="Yes","Optional",F4) -> 794.82415 | F4: =IF(SUMIFS('CF CSV Upload'!P:P,'CF CSV Upload'!A:A,'Customer Summary'!C4,'CF CSV Upload'!Q:Q,"Yes")=0,"n/a",SUMIFS('CF CSV Upload'!P:P,'CF CSV Upload'!A:A,'Customer Summary'!C4,'CF CSV Upload'!Q:Q,"Yes")) -> 794.82415
B5: =B4+1 -> 2 | C5: Condensation control: Supply and install Wall Mounted Dryaire system & required accessories | D5: No | E5: =IF(D5="Yes","Optional",F5) -> n/a | F5: =IF(SUMIFS('CF CSV Upload'!P:P,'CF CSV Upload'!A:A,'Customer Summary'!C5,'CF CSV Upload'!Q:Q,"Yes")=0,"n/a",SUMIFS('CF CSV Upload'!P:P,'CF CSV Upload'!A:A,'Customer Summary'!C5,'CF CSV Upload'!Q:Q,"Yes")) -> n/a
B6: =B5+1 -> 3 | C6: Condensation control: Supply and install Trickle & Boost Fan | D6: No | E6: =IF(D6="Yes","Optional",F6) -> 915.75 | F6: =IF(SUMIFS('CF CSV Upload'!P:P,'CF CSV Upload'!A:A,'Customer Summary'!C6,'CF CSV Upload'!Q:Q,"Yes")=0,"n/a",SUMIFS('CF CSV Upload'!P:P,'CF CSV Upload'!A:A,'Customer Summary'!C6,'CF CSV Upload'!Q:Q,"Yes")) -> 915.75
B7: =B6+1 -> 4 | C7: Condensation control: Supply and install Dryaire Cpass Insulated Pullcord Passive Vent | D7: No | E7: =IF(D7="Yes","Optional",F7) -> n/a | F7: =IF(SUMIFS('CF CSV Upload'!P:P,'CF CSV Upload'!A:A,'Customer Summary'!C7,'CF CSV Upload'!Q:Q,"Yes")=0,"n/a",SUMIFS('CF CSV Upload'!P:P,'CF CSV Upload'!A:A,'Customer Summary'!C7,'CF CSV Upload'!Q:Q,"Yes")) -> n/a
B8: =B7+1 -> 5 | C8: Condensation control: Supply and install Dryaire CVent | D8: No | E8: =IF(D8="Yes","Optional",F8) -> n/a | F8: =IF(SUMIFS('CF CSV Upload'!P:P,'CF CSV Upload'!A:A,'Customer Summary'!C8,'CF CSV Upload'!Q:Q,"Yes")=0,"n/a",SUMIFS('CF CSV Upload'!P:P,'CF CSV Upload'!A:A,'Customer Summary'!C8,'CF CSV Upload'!Q:Q,"Yes")) -> n/a
B9: =B8+1 -> 6 | C9: Joinery: Supply and fit boxwork for ducting | D9: Yes | E9: =IF(D9="Yes","Optional",F9) -> Optional | F9: =IF(SUMIFS('CF CSV Upload'!P:P,'CF CSV Upload'!A:A,'Customer Summary'!C9,'CF CSV Upload'!Q:Q,"Yes")=0,"n/a",SUMIFS('CF CSV Upload'!P:P,'CF CSV Upload'!A:A,'Customer Summary'!C9,'CF CSV Upload'!Q:Q,"Yes")) -> n/a
B10: =B9+1 -> 7 | C10: New hatch and ladder: Create larger opening, install new sturdy hatch and ladder to loft entry | D10: Yes | E10: =IF(D10="Yes","Optional",F10) -> Optional | F10: =IF(SUMIFS('CF CSV Upload'!P:P,'CF CSV Upload'!A:A,'Customer Summary'!C10,'CF CSV Upload'!Q:Q,"Yes")=0,"n/a",SUMIFS('CF CSV Upload'!P:P,'CF CSV Upload'!A:A,'Customer Summary'!C10,'CF CSV Upload'!Q:Q,"Yes")) -> n/a
B11: =B10+1 -> 8 | C11: Loft opening: Enlarge existing loft opening and install new hatch lid | D11: Yes | E11: =IF(D11="Yes","Optional",F11) -> Optional | F11: =IF(SUMIFS('CF CSV Upload'!P:P,'CF CSV Upload'!A:A,'Customer Summary'!C11,'CF CSV Upload'!Q:Q,"Yes")=0,"n/a",SUMIFS('CF CSV Upload'!P:P,'CF CSV Upload'!A:A,'Customer Summary'!C11,'CF CSV Upload'!Q:Q,"Yes")) -> n/a
B12: =B11+1 -> 9 | C12: Remedial treatments: Mould treatment | D12: No | E12: =IF(D12="Yes","Optional",F12) -> 95.79 | F12: =IF(SUMIFS('CF CSV Upload'!P:P,'CF CSV Upload'!A:A,'Customer Summary'!C12,'CF CSV Upload'!Q:Q,"Yes")=0,"n/a",SUMIFS('CF CSV Upload'!P:P,'CF CSV Upload'!A:A,'Customer Summary'!C12,'CF CSV Upload'!Q:Q,"Yes")) -> 95.79
B13: =B12+1 -> 10 | C13: Asbestos Testing | D13: Yes | E13: =IF(D13="Yes","Optional",F13) -> Optional | F13: =IF(SUMIFS('CF CSV Upload'!P:P,'CF CSV Upload'!A:A,'Customer Summary'!C13,'CF CSV Upload'!Q:Q,"Yes")=0,"n/a",SUMIFS('CF CSV Upload'!P:P,'CF CSV Upload'!A:A,'Customer Summary'!C13,'CF CSV Upload'!Q:Q,"Yes")) -> n/a
B14: =B13+1 -> 11 | C14: Airbricks | D14: No | E14: =IF(D14="Yes","Optional",F14) -> n/a | F14: =IF(SUMIFS('CF CSV Upload'!P:P,'CF CSV Upload'!A:A,'Customer Summary'!C14,'CF CSV Upload'!Q:Q,"Yes")=0,"n/a",SUMIFS('CF CSV Upload'!P:P,'CF CSV Upload'!A:A,'Customer Summary'!C14,'CF CSV Upload'!Q:Q,"Yes")) -> n/a
B15: =B14+1 -> 12 | C15: Project Specific Overheads | D15: No | E15: =IF(D15="Yes","Optional",F15) -> 139.932 | F15: =IF(SUMIFS('CF CSV Upload'!P:P,'CF CSV Upload'!A:A,'Customer Summary'!C15,'CF CSV Upload'!Q:Q,"Yes")=0,"n/a",SUMIFS('CF CSV Upload'!P:P,'CF CSV Upload'!A:A,'Customer Summary'!C15,'CF CSV Upload'!Q:Q,"Yes")) -> 139.932
B16: Totals
C17: Sub Total | E17: =SUM(E4:E15) -> 1946.2961 | F17: =SUM(F4:F15) -> 1946.2961
C18: Vat at 20% | E18: =E17*0.2 -> 389.25923 | F18: =F17*0.2 -> 389.25923
C19: Total | E19: =SUM(E17:E18) -> 2335.5554 | F19: =SUM(F17:F18) -> 2335.5554
C21: Start of works deposit at 50% | D21: Ex. VAT | E21: =E22/6*5 -> 973.14807 | F21: =F22/6*5 -> 973.14807
D22: Inc. VAT | E22: =E19*0.5 -> 1167.7777 | F22: =F19*0.5 -> 1167.7777

Sheet Office Notes
A1: Add notes below that the office need to consider when compiling the estimate and report.

Sheet CAF1 Form
B1: On Site Acceptance Form (CAF1).
B3: Enquiry ID:
B4: Client Name
B5: Address 1
B6: Address 2
B7: Address 3
B8: Address 4
B9: Postcode
B11: I wish to proceed with the woks specified below. (tick items required and total cost)
B13: Operation | I13: Price | K13: Tick
B14: Damp Proofing
B15: Timber treatments/replacements
B16: Condensation
B17: Wall Ties
B18: Other works
B19: Subtotal
B20: VAT
B21: Total
B22: Deposit
B24: I accept the company terms and conditions of contract which I have viewed at the link below and I have paid my deposit with this order.
B25: https://www.tyneteesdampproofing.co.uk/terms-and-conditions/
B27: I wish the work to commence before the 14 day cooling off period and waive my consumer rights (please sign to confirm)
B29: Signed: | I29: Date:

Sheet Sub Contractor Costs
B2: Sub Contractor Costs
B3: Project Details
B4: Enquiry number | D4: =Costing!E4 -> PRONE455DN
B5: =[1]Details!$B$7 -> Client Name | D5: =Costing!E7 -> Finest Properties
B6: =[1]Details!$B$8 -> First Line of site address | D6: =Costing!E8 -> Clive House
B7: =[1]Details!$B$9 -> Town / City | D7: =Costing!E9 -> Appletree Lane
B8: =[1]Details!$B$10 -> County | D8: =Costing!E10 -> Corbridge
B9: =[1]Details!$B$11 -> Site Post Code | D9: =Costing!E11 -> NE45 5DN
B10: # | C10: Area of Works | D10: Costs (Ex VAT) | E10: Assigned to / Comments: | G10: Total Projected Hours
B11: 1 | C11: ='Customer Summary'!C4 -> Condensation control: Supply and install Loft Dryaire system & required accessories | D11: =Costing!V25 -> 70 | G11: =Costing!O25 -> 2.5
B12: =B11+1 -> 2 | C12: ='Customer Summary'!C5 -> Condensation control: Supply and install Wall Mounted Dryaire system & required accessories | D12: =Costing!V42 -> 0 | G12: =Costing!O42 -> 0
B13: =B12+1 -> 3 | C13: ='Customer Summary'!C6 -> Condensation control: Supply and install Trickle & Boost Fan | D13: =Costing!V49 -> 210 | G13: =Costing!O49 -> 7.5
B14: =B13+1 -> 4 | C14: ='Customer Summary'!C7 -> Condensation control: Supply and install Dryaire Cpass Insulated Pullcord Passive Vent | D14: =Costing!V54 -> 0 | G14: =Costing!O54 -> 0
B15: =B14+1 -> 5 | C15: ='Customer Summary'!C8 -> Condensation control: Supply and install Dryaire CVent | D15: =Costing!V59 -> 0 | G15: =Costing!O59 -> 0
B16: =B15+1 -> 6 | C16: ='Customer Summary'!C9 -> Joinery: Supply and fit boxwork for ducting | D16: =Costing!V63 -> 0 | G16: =Costing!O63 -> 0
B17: =B16+1 -> 7 | C17: ='Customer Summary'!C10 -> New hatch and ladder: Create larger opening, install new sturdy hatch and ladder to loft entry | D17: =Costing!V67 -> 0 | G17: =Costing!V67 -> 0
B18: =B17+1 -> 8 | C18: ='Customer Summary'!C11 -> Loft opening: Enlarge existing loft opening and install new hatch lid | D18: =Costing!V71 -> 0 | G18: =Costing!V71 -> 0
B19: =B18+1 -> 9 | C19: ='Customer Summary'!C12 -> Remedial treatments: Mould treatment | D19: =Costing!V75 -> 42 | G19: =Costing!V75 -> 42
B20: =B19+1 -> 10 | C20: ='Customer Summary'!C13 -> Asbestos Testing | D20: =Costing!V79 -> 0 | G20: =Costing!V79 -> 0
B21: =B20+1 -> 11 | C21: ='Customer Summary'!C14 -> Airbricks | D21: =Costing!V85 -> 0 | G21: =Costing!V85 -> 0
C23: Total | D23: =SUM(D11:D22) -> 322 | G23: =SUM(G11:G22) -> 52

Sheet CF CSV Upload
A1: Section | B1: Section Description | C1: Item Name | D1: Quantity | E1: Unit Cost | F1: Unit | G1: Cost Code | H1: Markup | I1: Markup Type | J1: Item Type | K1: Is Taxable | L1: Is Optional | M1: Assigned To | N1: CF IGNORE - LINE VALUE | O1: CF IGNORE - Zero value Section Validation | P1: CF IGNORE - LINE VALUE FOR CUSTOMER SUMMARY | Q1: CF IGNORE - INCLUDE PRICE IN CUSTOMER SUMMARY
A2: ='Customer Summary'!C4 -> Condensation control: Supply and install Loft Dryaire system & required accessories | C2: =Costing!B21 -> VA Pozidry loft unit - heated | D2: =Costing!F21 -> 1 | E2: =Costing!I21 -> 307.9235 | F2: =Costing!G21 -> Each | G2: Condensation Materials | H2: =Costing!J21*100 -> 40 | I2: % | J2: MTL | K2: Yes | L2: No | M2: =IF(J2="MTL","Preservation Shop","") -> Preservation Shop | N2: =D2*E2 -> 307.9235 | O2: DELETE | P2: =N2*(1+(H2/100)) -> 431.0929 | Q2: No
A3: =A2 -> Condensation control: Supply and install Loft Dryaire system & required accessories | C3: =Costing!B22 -> VA Pozidry loft unit - unheated | D3: =Costing!F22 -> 0 | E3: =Costing!I22 -> 294.462 | F3: =Costing!G22 -> Each | G3: Condensation Materials | H3: =Costing!J22*100 -> 40 | I3: % | J3: MTL | K3: Yes | L3: No | M3: =IF(J3="MTL","Preservation Shop","") -> Preservation Shop | N3: =D3*E3 -> 0 | O3: DELETE | P3: =N3*(1+(H3/100)) -> 0 | Q3: No
A4: =A3 -> Condensation control: Supply and install Loft Dryaire system & required accessories | C4: =Costing!B23 -> Electrical Pack - fused spur, cable, JB | D4: =Costing!F23 -> 0 | E4: =Costing!I23 -> 11.837 | F4: =Costing!G23 -> Each | G4: Condensation Materials | H4: =Costing!J23*100 -> 30 | I4: % | J4: MTL | K4: Yes | L4: No | M4: =IF(J4="MTL","Preservation Shop","") -> Preservation Shop | N4: =D4*E4 -> 0 | O4: DELETE | P4: =N4*(1+(H4/100)) -> 0 | Q4: No
A5: =A4 -> Condensation control: Supply and install Loft Dryaire system & required accessories | C5: =Costing!B24 -> Sarkvents | D5: =Costing!F24 -> 0 | E5: =Costing!I24 -> 2.85 | F5: =Costing!G24 -> Each | G5: Condensation Materials | H5: =Costing!J24*100 -> 30 | I5: % | J5: MTL | K5: Yes | L5: No | M5: =IF(J5="MTL","Preservation Shop","") -> Preservation Shop | N5: =D5*E5 -> 0 | O5: DELETE | P5: =N5*(1+(H5/100)) -> 0 | Q5: No
A6: =A5 -> Condensation control: Supply and install Loft Dryaire system & required accessories | C6: =Costing!M21 -> VA Pozidry loft unit - heated | D6: =Costing!O21 -> 2.5 | E6: =Costing!Q21 -> 29.0985 | F6: Hours | G6: Condensation Labour | H6: =Costing!R21*100 -> 400 | I6: % | J6: LBR | K6: Yes | L6: No | M6: =IF(J6="MTL","Preservation Shop","") | N6: =D6*E6 -> 72.74625 | O6: DELETE | P6: =N6*(1+(H6/100)) -> 363.73125 | Q6: No
A7: =A6 -> Condensation control: Supply and install Loft Dryaire system & required accessories | C7: =Costing!M22 -> VA Pozidry loft unit - unheated | D7: =Costing!O22 -> 0 | E7: =Costing!Q22 -> 29.0985 | F7: Hours | G7: Condensation Labour | H7: =Costing!R22*100 -> 400 | I7: % | J7: LBR | K7: Yes | L7: No | M7: =IF(J7="MTL","Preservation Shop","") | N7: =D7*E7 -> 0 | O7: DELETE | P7: =N7*(1+(H7/100)) -> 0 | Q7: No
A8: =A7 -> Condensation control: Supply and install Loft Dryaire system & required accessories | C8: =Costing!M23 -> Electrical Pack - fused spur, cable, JB | D8: =Costing!O23 -> 0 | E8: =Costing!Q23 -> 29.0985 | F8: Hours | G8: Condensation Labour | H8: =Costing!R23*100 -> 100 | I8: % | J8: LBR | K8: Yes | L8: No | M8: =IF(J8="MTL","Preservation Shop","") | N8: =D8*E8 -> 0 | O8: DELETE | P8: =N8*(1+(H8/100)) -> 0 | Q8: No
A9: =A8 -> Condensation control: Supply and install Loft Dryaire system & required accessories | C9: =Costing!M24 -> Sarkvents | D9: =Costing!O24 -> 0 | E9: =Costing!Q24 -> 29.0985 | F9: Hours | G9: Condensation Labour | H9: =Costing!R24*100 -> 100 | I9: % | J9: LBR | K9: Yes | L9: No | M9: =IF(J9="MTL","Preservation Shop","") | N9: =D9*E9 -> 0 | O9: DELETE | P9: =N9*(1+(H9/100)) -> 0 | Q9: No
A10: =A9 -> Condensation control: Supply and install Loft Dryaire system & required accessories | C10: =_xlfn.CONCAT(A10," - Materials") -> Condensation control: Supply and install Loft Dryaire system & required accessories - Materials | D10: 1 | E10: =N10 -> 307.9235 | F10: EACH | G10: Condensation Materials | H10: =((P10-N10)/N10)*100 -> 40 | I10: % | J10: MTL | K10: Yes | L10: ='Customer Summary'!D4 -> No | M10: =IF(J10="MTL","Preservation Shop","") -> Preservation Shop | N10: =SUM(N2:N5) -> 307.9235 | O10: =IF(N10=0,"DELETE","LEAVE") -> LEAVE | P10: =SUM(P2:P5) -> 431.0929 | Q10: Yes
A11: =A10 -> Condensation control: Supply and install Loft Dryaire system & required accessories | C11: =_xlfn.CONCAT(A11," - Labour") -> Condensation control: Supply and install Loft Dryaire system & required accessories - Labour | D11: =SUM(D6:D9) -> 2.5 | E11: =N11/D11 -> 29.0985 | F11: Hours | G11: Condensation Labour | H11: =((P11-N11)/N11)*100 -> 400 | I11: % | J11: LBR | K11: Yes | L11: =L10 -> No | M11: =IF(J11="MTL","Preservation Shop","") | N11: =SUM(N6:N9) -> 72.74625 | O11: =IF(N11=0,"DELETE","LEAVE") -> LEAVE | P11: =SUM(P6:P9) -> 363.73125 | Q11: Yes
O12: DELETE
A13: ='Customer Summary'!C5 -> Condensation control: Supply and install Wall Mounted Dryaire system & required accessories | C13: =Costing!B28 -> VA Pozidry Compact wall mounted unit | D13: =Costing!F28 -> 0 | E13: =Costing!I28 -> 273.74 | F13: =Costing!G28 -> Each | G13: Condensation Materials | H13: =Costing!J28*100 -> 40 | I13: % | J13: MTL | K13: Yes | L13: No | M13: =IF(J13="MTL","Preservation Shop","") -> Preservation Shop | N13: =D13*E13 -> 0 | O13: DELETE | P13: =N13*(1+(H13/100)) -> 0 | Q13: No
A14: =A13 -> Condensation control: Supply and install Wall Mounted Dryaire system & required accessories | C14: =Costing!B29 -> Electrical Pack - fused spur, cable, JB | D14: =Costing!F29 -> 0 | E14: =Costing!I29 -> 12.46 | F14: =Costing!G29 -> Each | G14: Condensation Materials | H14: =Costing!J29*100 -> 30 | I14: % | J14: MTL | K14: Yes | L14: No | M14: =IF(J14="MTL","Preservation Shop","") -> Preservation Shop | N14: =D14*E14 -> 0 | O14: DELETE | P14: =N14*(1+(H14/100)) -> 0 | Q14: No
A15: =A14 -> Condensation control: Supply and install Wall Mounted Dryaire system & required accessories | C15: =Costing!B30 -> Ducting - 1m length | D15: =Costing!F30 -> 0 | E15: =Costing!I30 -> 3.85 | F15: =Costing!G30 -> Each | G15: Condensation Materials | H15: =Costing!J30*100 -> 30 | I15: % | J15: MTL | K15: Yes | L15: No | M15: =IF(J15="MTL","Preservation Shop","") -> Preservation Shop | N15: =D15*E15 -> 0 | O15: DELETE | P15: =N15*(1+(H15/100)) -> 0 | Q15: No
A16: =A15 -> Condensation control: Supply and install Wall Mounted Dryaire system & required accessories | C16: =Costing!B31 -> Ducting - round elbow | D16: =Costing!F31 -> 0 | E16: =Costing!I31 -> 2.78 | F16: =Costing!G31 -> Each | G16: Condensation Materials | H16: =Costing!J31*100 -> 30 | I16: % | J16: MTL | K16: Yes | L16: No | M16: =IF(J16="MTL","Preservation Shop","") -> Preservation Shop | N16: =D16*E16 -> 0 | O16: DELETE | P16: =N16*(1+(H16/100)) -> 0 | Q16: No
A17: =A16 -> Condensation control: Supply and install Wall Mounted Dryaire system & required accessories | C17: =Costing!B32 -> Ducting - round - straight conn | D17: =Costing!F32 -> 0 | E17: =Costing!I32 -> 0.52 | F17: =Costing!G32 -> Each | G17: Condensation Materials | H17: =Costing!J32*100 -> 30 | I17: % | J17: MTL | K17: Yes | L17: No | M17: =IF(J17="MTL","Preservation Shop","") -> Preservation Shop | N17: =D17*E17 -> 0 | O17: DELETE | P17: =N17*(1+(H17/100)) -> 0 | Q17: No
A18: =A17 -> Condensation control: Supply and install Wall Mounted Dryaire system & required accessories | C18: =Costing!B33 -> Ducting - round 1m | D18: =Costing!F33 -> 0 | E18: =Costing!I33 -> 3.85 | F18: =Costing!G33 -> Each | G18: Condensation Materials | H18: =Costing!J33*100 -> 30 | I18: % | J18: MTL | K18: Yes | L18: No | M18: =IF(J18="MTL","Preservation Shop","") -> Preservation Shop | N18: =D18*E18 -> 0 | O18: DELETE | P18: =N18*(1+(H18/100)) -> 0 | Q18: No
A19: =A18 -> Condensation control: Supply and install Wall Mounted Dryaire system & required accessories | C19: =Costing!B34 -> Ducting - flat to round adaptor | D19: =Costing!F34 -> 0 | E19: =Costing!I34 -> 1.63 | F19: =Costing!G34 -> Each | G19: Condensation Materials | H19: =Costing!J34*100 -> 30 | I19: % | J19: MTL | K19: Yes | L19: No | M19: =IF(J19="MTL","Preservation Shop","") -> Preservation Shop | N19: =D19*E19 -> 0 | O19: DELETE | P19: =N19*(1+(H19/100)) -> 0 | Q19: No
A20: =A19 -> Condensation control: Supply and install Wall Mounted Dryaire system & required accessories | C20: =Costing!B35 -> Ducting - flat straight connector | D20: =Costing!F35 -> 0 | E20: =Costing!I35 -> 1.14 | F20: =Costing!G35 -> Each | G20: Condensation Materials | H20: =Costing!J35*100 -> 30 | I20: % | J20: MTL | K20: Yes | L20: No | M20: =IF(J20="MTL","Preservation Shop","") -> Preservation Shop | N20: =D20*E20 -> 0 | O20: DELETE | P20: =N20*(1+(H20/100)) -> 0 | Q20: No
A21: =A20 -> Condensation control: Supply and install Wall Mounted Dryaire system & required accessories | C21: =Costing!B36 -> Ducting - flat horizontal bend | D21: =Costing!F36 -> 0 | E21: =Costing!I36 -> 3.01 | F21: =Costing!G36 -> Each | G21: Condensation Materials | H21: =Costing!J36*100 -> 30 | I21: % | J21: MTL | K21: Yes | L21: No | M21: =IF(J21="MTL","Preservation Shop","") -> Preservation Shop | N21: =D21*E21 -> 0 | O21: DELETE | P21: =N21*(1+(H21/100)) -> 0 | Q21: No
A22: =A21 -> Condensation control: Supply and install Wall Mounted Dryaire system & required accessories | C22: =Costing!B37 -> Ducting - flat vertical bend | D22: =Costing!F37 -> 0 | E22: =Costing!I37 -> 3.01 | F22: =Costing!G37 -> Each | G22: Condensation Materials | H22: =Costing!J37*100 -> 30 | I22: % | J22: MTL | K22: Yes | L22: No | M22: =IF(J22="MTL","Preservation Shop","") -> Preservation Shop | N22: =D22*E22 -> 0 | O22: DELETE | P22: =N22*(1+(H22/100)) -> 0 | Q22: No
A23: =A22 -> Condensation control: Supply and install Wall Mounted Dryaire system & required accessories | C23: =Costing!B38 -> Ducting - flat - 1m | D23: =Costing!F38 -> 0 | E23: =Costing!I38 -> 2.87 | F23: =Costing!G38 -> Each | G23: Condensation Materials | H23: =Costing!J38*100 -> 30 | I23: % | J23: MTL | K23: Yes | L23: No | M23: =IF(J23="MTL","Preservation Shop","") -> Preservation Shop | N23: =D23*E23 -> 0 | O23: DELETE | P23: =N23*(1+(H23/100)) -> 0 | Q23: No
A24: =A23 -> Condensation control: Supply and install Wall Mounted Dryaire system & required accessories | C24: =Costing!B39 -> Ducting - insulated flexi (3m Length) | D24: =Costing!F39 -> 0 | E24: =Costing!I39 -> 2.5 | F24: =Costing!G39 -> Each | G24: Condensation Materials | H24: =Costing!J39*100 -> 30 | I24: % | J24: MTL | K24: Yes | L24: No | M24: =IF(J24="MTL","Preservation Shop","") -> Preservation Shop | N24: =D24*E24 -> 0 | O24: DELETE | P24: =N24*(1+(H24/100)) -> 0 | Q24: No
A25: =A24 -> Condensation control: Supply and install Wall Mounted Dryaire system & required accessories | C25: =Costing!B40 -> Grille | D25: =Costing!F40 -> 0 | E25: =Costing!I40 -> 2.42 | F25: =Costing!G40 -> Each | G25: Condensation Materials | H25: =Costing!J40*100 -> 30 | I25: % | J25: MTL | K25: Yes | L25: No | M25: =IF(J25="MTL","Preservation Shop","") -> Preservation Shop | N25: =D25*E25 -> 0 | O25: DELETE | P25: =N25*(1+(H25/100)) -> 0 | Q25: No
A26: =A25 -> Condensation control: Supply and install Wall Mounted Dryaire system & required accessories | C26: =Costing!B41 -> Diamond core 107mm hole | D26: =Costing!F41 -> 0 | E26: =Costing!I41 -> 0 | F26: =Costing!G41 -> Each | G26: Condensation Materials | H26: =Costing!J41*100 -> 30 | I26: % | J26: MTL | K26: Yes | L26: No | M26: =IF(J26="MTL","Preservation Shop","") -> Preservation Shop | N26: =D26*E26 -> 0 | O26: DELETE | P26: =N26*(1+(H26/100)) -> 0 | Q26: No
A27: =A26 -> Condensation control: Supply and install Wall Mounted Dryaire system & required accessories | C27: =Costing!M28 -> VA Pozidry Compact wall mounted unit | D27: =Costing!O28 -> 0 | E27: =Costing!Q28 -> 30.63 | F27: Hours | G27: Condensation Labour | H27: =Costing!R28*100 -> 300 | I27: % | J27: LBR | K27: Yes | L27: No | M27: =IF(J27="MTL","Preservation Shop","") | N27: =D27*E27 -> 0 | O27: DELETE | P27: =N27*(1+(H27/100)) -> 0 | Q27: No
A28: =A27 -> Condensation control: Supply and install Wall Mounted Dryaire system & required accessories | C28: =Costing!M29 -> Electrical Pack - fused spur, cable, JB | D28: =Costing!O29 -> 0 | E28: =Costing!Q29 -> 30.63 | F28: Hours | G28: Condensation Labour | H28: =Costing!R29*100 -> 100 | I28: % | J28: LBR | K28: Yes | L28: No | M28: =IF(J28="MTL","Preservation Shop","") | N28: =D28*E28 -> 0 | O28: DELETE | P28: =N28*(1+(H28/100)) -> 0 | Q28: No
A29: =A28 -> Condensation control: Supply and install Wall Mounted Dryaire system & required accessories | C29: =Costing!M30 -> Ducting - 1m length | D29: =Costing!O30 -> 0 | E29: =Costing!Q30 -> 30.63 | F29: Hours | G29: Condensation Labour | H29: =Costing!R30*100 -> 100 | I29: % | J29: LBR | K29: Yes | L29: No | M29: =IF(J29="MTL","Preservation Shop","") | N29: =D29*E29 -> 0 | O29: DELETE | P29: =N29*(1+(H29/100)) -> 0 | Q29: No
A30: =A29 -> Condensation control: Supply and install Wall Mounted Dryaire system & required accessories | C30: =Costing!M31 -> Ducting - round elbow | D30: =Costing!O31 -> 0 | E30: =Costing!Q31 -> 30.63 | F30: Hours | G30: Condensation Labour | H30: =Costing!R31*100 -> 100 | I30: % | J30: LBR | K30: Yes | L30: No | M30: =IF(J30="MTL","Preservation Shop","") | N30: =D30*E30 -> 0 | O30: DELETE | P30: =N30*(1+(H30/100)) -> 0 | Q30: No
A31: =A30 -> Condensation control: Supply and install Wall Mounted Dryaire system & required accessories | C31: =Costing!M32 -> Ducting - round - straight conn | D31: =Costing!O32 -> 0 | E31: =Costing!Q32 -> 30.63 | F31: Hours | G31: Condensation Labour | H31: =Costing!R32*100 -> 100 | I31: % | J31: LBR | K31: Yes | L31: No | M31: =IF(J31="MTL","Preservation Shop","") | N31: =D31*E31 -> 0 | O31: DELETE | P31: =N31*(1+(H31/100)) -> 0 | Q31: No
A32: =A31 -> Condensation control: Supply and install Wall Mounted Dryaire system & required accessories | C32: =Costing!M33 -> Ducting - round 1m | D32: =Costing!O33 -> 0 | E32: =Costing!Q33 -> 30.63 | F32: Hours | G32: Condensation Labour | H32: =Costing!R33*100 -> 100 | I32: % | J32: LBR | K32: Yes | L32: No | M32: =IF(J32="MTL","Preservation Shop","") | N32: =D32*E32 -> 0 | O32: DELETE | P32: =N32*(1+(H32/100)) -> 0 | Q32: No
A33: =A32 -> Condensation control: Supply and install Wall Mounted Dryaire system & required accessories | C33: =Costing!M34 -> Ducting - flat to round adaptor | D33: =Costing!O34 -> 0 | E33: =Costing!Q34 -> 30.63 | F33: Hours | G33: Condensation Labour | H33: =Costing!R34*100 -> 100 | I33: % | J33: LBR | K33: Yes | L33: No | M33: =IF(J33="MTL","Preservation Shop","") | N33: =D33*E33 -> 0 | O33: DELETE | P33: =N33*(1+(H33/100)) -> 0 | Q33: No
A34: =A33 -> Condensation control: Supply and install Wall Mounted Dryaire system & required accessories | C34: =Costing!M35 -> Ducting - flat straight connector | D34: =Costing!O35 -> 0 | E34: =Costing!Q35 -> 30.63 | F34: Hours | G34: Condensation Labour | H34: =Costing!R35*100 -> 100 | I34: % | J34: LBR | K34: Yes | L34: No | M34: =IF(J34="MTL","Preservation Shop","") | N34: =D34*E34 -> 0 | O34: DELETE | P34: =N34*(1+(H34/100)) -> 0 | Q34: No
A35: =A34 -> Condensation control: Supply and install Wall Mounted Dryaire system & required accessories | C35: =Costing!M36 -> Ducting - flat horizontal bend | D35: =Costing!O36 -> 0 | E35: =Costing!Q36 -> 30.63 | F35: Hours | G35: Condensation Labour | H35: =Costing!R36*100 -> 100 | I35: % | J35: LBR | K35: Yes | L35: No | M35: =IF(J35="MTL","Preservation Shop","") | N35: =D35*E35 -> 0 | O35: DELETE | P35: =N35*(1+(H35/100)) -> 0 | Q35: No
A36: =A35 -> Condensation control: Supply and install Wall Mounted Dryaire system & required accessories | C36: =Costing!M37 -> Ducting - flat vertical bend | D36: =Costing!O37 -> 0 | E36: =Costing!Q37 -> 30.63 | F36: Hours | G36: Condensation Labour | H36: =Costing!R37*100 -> 100 | I36: % | J36: LBR | K36: Yes | L36: No | M36: =IF(J36="MTL","Preservation Shop","") | N36: =D36*E36 -> 0 | O36: DELETE | P36: =N36*(1+(H36/100)) -> 0 | Q36: No
A37: =A36 -> Condensation control: Supply and install Wall Mounted Dryaire system & required accessories | C37: =Costing!M38 -> Ducting - flat - 1m | D37: =Costing!O38 -> 0 | E37: =Costing!Q38 -> 30.63 | F37: Hours | G37: Condensation Labour | H37: =Costing!R38*100 -> 100 | I37: % | J37: LBR | K37: Yes | L37: No | M37: =IF(J37="MTL","Preservation Shop","") | N37: =D37*E37 -> 0 | O37: DELETE | P37: =N37*(1+(H37/100)) -> 0 | Q37: No
A38: =A37 -> Condensation control: Supply and install Wall Mounted Dryaire system & required accessories | C38: =Costing!M39 -> Ducting - insulated flexi (3m Length) | D38: =Costing!O39 -> 0 | E38: =Costing!Q39 -> 30.63 | F38: Hours | G38: Condensation Labour | H38: =Costing!R39*100 -> 100 | I38: % | J38: LBR | K38: Yes | L38: No | M38: =IF(J38="MTL","Preservation Shop","") | N38: =D38*E38 -> 0 | O38: DELETE | P38: =N38*(1+(H38/100)) -> 0 | Q38: No
... A40: =A39 -> Condensation control: Supply and install Wall Mounted Dryaire system & required accessories | C40: =Costing!M41 -> Diamond core 107mm hole | D40: =Costing!O41 -> 0 | E40: =Costing!Q41 -> 30.63 | F40: Hours | G40: Condensation Labour | H40: =Costing!R41*100 -> 100 | I40: % | J40: LBR | K40: Yes | L40: No | M40: =IF(J40="MTL","Preservation Shop","") | N40: =D40*E40 -> 0 | O40: DELETE | P40: =N40*(1+(H40/100)) -> 0 | Q40: No
A41: =A40 -> Condensation control: Supply and install Wall Mounted Dryaire system & required accessories | C41: =_xlfn.CONCAT(A41," - Materials") -> Condensation control: Supply and install Wall Mounted Dryaire system & required accessories - Materials | D41: 1 | E41: =N41 -> 0 | F41: EACH | G41: Condensation Materials | H41: =((P41-N41)/N41)*100 -> #DIV/0! | I41: % | J41: MTL | K41: Yes | L41: ='Customer Summary'!D5 -> No | M41: =IF(J41="MTL","Preservation Shop","") -> Preservation Shop | N41: =SUM(N13:N26) -> 0 | O41: =IF(N41=0,"DELETE","LEAVE") -> DELETE | P41: =SUM(P13:P26) -> 0 | Q41: Yes
A42: =A41 -> Condensation control: Supply and install Wall Mounted Dryaire system & required accessories | C42: =_xlfn.CONCAT(A42," - Labour") -> Condensation control: Supply and install Wall Mounted Dryaire system & required accessories - Labour | D42: =SUM(D27:D40) -> 0 | E42: =N42/D42 -> #DIV/0! | F42: Hours | G42: Condensation Labour | H42: =((P42-N42)/N42)*100 -> #DIV/0! | I42: % | J42: LBR | K42: Yes | L42: =L41 -> No | M42: =IF(J42="MTL","Preservation Shop","") | N42: =SUM(N27:N40) -> 0 | O42: =IF(N42=0,"DELETE","LEAVE") -> DELETE | P42: =SUM(P27:P40) -> 0 | Q42: Yes
O43: DELETE
A44: ='Customer Summary'!C6 -> Condensation control: Supply and install Trickle & Boost Fan | C44: =Costing!B45 -> Trickle and boost humidistat fan (greenwood) | D44: =Costing!F45 -> 5 | E44: =Costing!I45 -> 70.2 | F44: =Costing!G45 -> Each | G44: Condensation Materials | H44: =Costing!J45*100 -> 30 | I44: % | J44: MTL | K44: Yes | L44: No | M44: =IF(J44="MTL","Preservation Shop","") -> Preservation Shop | N44: =D44*E44 -> 351 | O44: DELETE | P44: =N44*(1+(H44/100)) -> 456.3 | Q44: No
A45: =A44 -> Condensation control: Supply and install Trickle & Boost Fan | C45: =Costing!B46 -> Electrical Pack - fused spur, cable, JB | D45: =Costing!F46 -> 0 | E45: =Costing!I46 -> 12.46 | F45: =Costing!G46 -> Each | G45: Condensation Materials | H45: =Costing!J46*100 -> 30 | I45: % | J45: MTL | K45: Yes | L45: No | M45: =IF(J45="MTL","Preservation Shop","") -> Preservation Shop | N45: =D45*E45 -> 0 | O45: DELETE | P45: =N45*(1+(H45/100)) -> 0 | Q45: No
A46: =A45 -> Condensation control: Supply and install Trickle & Boost Fan | C46: =Costing!B47 -> Grille | D46: =Costing!F47 -> 0 | E46: =Costing!I47 -> 2.42 | F46: =Costing!G47 -> Each | G46: Condensation Materials | H46: =Costing!J47*100 -> 30 | I46: % | J46: MTL | K46: Yes | L46: No | M46: =IF(J46="MTL","Preservation Shop","") -> Preservation Shop | N46: =D46*E46 -> 0 | O46: DELETE | P46: =N46*(1+(H46/100)) -> 0 | Q46: No
A47: =A46 -> Condensation control: Supply and install Trickle & Boost Fan | C47: =Costing!B48 -> Diamond core 107mm hole | D47: =Costing!F48 -> 0 | E47: =Costing!I48 -> 0 | F47: =Costing!G48 -> Each | G47: Condensation Materials | H47: =Costing!J48*100 -> 30 | I47: % | J47: MTL | K47: Yes | L47: No | M47: =IF(J47="MTL","Preservation Shop","") -> Preservation Shop | N47: =D47*E47 -> 0 | O47: DELETE | P47: =N47*(1+(H47/100)) -> 0 | Q47: No
A48: =A47 -> Condensation control: Supply and install Trickle & Boost Fan | C48: =Costing!M45 -> Trickle and boost humidistat fan (greenwood) | D48: =Costing!O45 -> 7.5 | E48: =Costing!Q45 -> 30.63 | F48: Hours | G48: Condensation Labour | H48: =Costing!R45*100 -> 100 | I48: % | J48: LBR | K48: Yes | L48: No | M48: =IF(J48="MTL","Preservation Shop","") | N48: =D48*E48 -> 229.725 | O48: DELETE | P48: =N48*(1+(H48/100)) -> 459.45 | Q48: No
A49: =A48 -> Condensation control: Supply and install Trickle & Boost Fan | C49: =Costing!M46 -> Electrical Pack - fused spur, cable, JB | D49: =Costing!O46 -> 0 | E49: =Costing!Q46 -> 30.63 | F49: Hours | G49: Condensation Labour | H49: =Costing!R46*100 -> 100 | I49: % | J49: LBR | K49: Yes | L49: No | M49: =IF(J49="MTL","Preservation Shop","") | N49: =D49*E49 -> 0 | O49: DELETE | P49: =N49*(1+(H49/100)) -> 0 | Q49: No
A50: =A49 -> Condensation control: Supply and install Trickle & Boost Fan | C50: =Costing!M47 -> Grille | D50: =Costing!O47 -> 0 | E50: =Costing!Q47 -> 30.63 | F50: Hours | G50: Condensation Labour | H50: =Costing!R47*100 -> 100 | I50: % | J50: LBR | K50: Yes | L50: No | M50: =IF(J50="MTL","Preservation Shop","") | N50: =D50*E50 -> 0 | O50: DELETE | P50: =N50*(1+(H50/100)) -> 0 | Q50: No
A51: =A50 -> Condensation control: Supply and install Trickle & Boost Fan | C51: =Costing!M48 -> Diamond core 107mm hole | D51: =Costing!O48 -> 0 | E51: =Costing!Q48 -> 30.63 | F51: Hours | G51: Condensation Labour | H51: =Costing!R48*100 -> 100 | I51: % | J51: LBR | K51: Yes | L51: No | M51: =IF(J51="MTL","Preservation Shop","") | N51: =D51*E51 -> 0 | O51: DELETE | P51: =N51*(1+(H51/100)) -> 0 | Q51: No
A52: =A51 -> Condensation control: Supply and install Trickle & Boost Fan | C52: =_xlfn.CONCAT(A52," - Materials") -> Condensation control: Supply and install Trickle & Boost Fan - Materials | D52: 1 | E52: =N52 -> 351 | F52: EACH | G52: Condensation Materials | H52: =((P52-N52)/N52)*100 -> 30 | I52: % | J52: MTL | K52: Yes | L52: ='Customer Summary'!D6 -> No | M52: =IF(J52="MTL","Preservation Shop","") -> Preservation Shop | N52: =SUM(N44:N47) -> 351 | O52: =IF(N52=0,"DELETE","LEAVE") -> LEAVE | P52: =SUM(P44:P47) -> 456.3 | Q52: Yes
A53: =A52 -> Condensation control: Supply and install Trickle & Boost Fan | C53: =_xlfn.CONCAT(A53," - Labour") -> Condensation control: Supply and install Trickle & Boost Fan - Labour | D53: =SUM(D48:D51) -> 7.5 | E53: =N53/D53 -> 30.63 | F53: Hours | G53: Condensation Labour | H53: =((P53-N53)/N53)*100 -> 100 | I53: % | J53: LBR | K53: Yes | L53: =L52 -> No | M53: =IF(J53="MTL","Preservation Shop","") | N53: =SUM(N48:N51) -> 229.725 | O53: =IF(N53=0,"DELETE","LEAVE") -> LEAVE | P53: =SUM(P48:P51) -> 459.45 | Q53: Yes
O54: DELETE
A55: ='Customer Summary'!C7 -> Condensation control: Supply and install Dryaire Cpass Insulated Pullcord Passive Vent | C55: =Costing!B52 -> Dryaire Cpass (plasmo) insulated pullcord passive vent | D55: =Costing!F52 -> 0 | E55: =Costing!I52 -> 36.18 | F55: =Costing!G52 -> Each | G55: Condensation Materials | H55: =Costing!J52*100 -> 30 | I55: % | J55: MTL | K55: Yes | L55: No | M55: =IF(J55="MTL","Preservation Shop","") -> Preservation Shop | N55: =D55*E55 -> 0 | O55: DELETE | P55: =N55*(1+(H55/100)) -> 0 | Q55: No
A56: =A55 -> Condensation control: Supply and install Dryaire Cpass Insulated Pullcord Passive Vent | C56: =Costing!B53 -> Diamond core 107mm hole | D56: =Costing!F53 -> 0 | E56: =Costing!I53 -> 0 | F56: =Costing!G53 -> Each | G56: Condensation Materials | H56: =Costing!J53*100 -> 30 | I56: % | J56: MTL | K56: Yes | L56: No | M56: =IF(J56="MTL","Preservation Shop","") -> Preservation Shop | N56: =D56*E56 -> 0 | O56: DELETE | P56: =N56*(1+(H56/100)) -> 0 | Q56: No
A57: =A56 -> Condensation control: Supply and install Dryaire Cpass Insulated Pullcord Passive Vent | C57: =Costing!M52 -> Dryaire Cpass (plasmo) insulated pullcord passive vent | D57: =Costing!O52 -> 0 | E57: =Costing!Q52 -> 30.63 | F57: Hours | G57: Condensation Labour | H57: =Costing!R52*100 -> 100 | I57: % | J57: LBR | K57: Yes | L57: No | M57: =IF(J57="MTL","Preservation Shop","") | N57: =D57*E57 -> 0 | O57: DELETE | P57: =N57*(1+(H57/100)) -> 0 | Q57: No
A58: =A57 -> Condensation control: Supply and install Dryaire Cpass Insulated Pullcord Passive Vent | C58: =Costing!M53 -> Diamond core 107mm hole | D58: =Costing!O53 -> 0 | E58: =Costing!Q53 -> 30.63 | F58: Hours | G58: Condensation Labour | H58: =Costing!R53*100 -> 100 | I58: % | J58: LBR | K58: Yes | L58: No | M58: =IF(J58="MTL","Preservation Shop","") | N58: =D58*E58 -> 0 | O58: DELETE | P58: =N58*(1+(H58/100)) -> 0 | Q58: No
A59: =A58 -> Condensation control: Supply and install Dryaire Cpass Insulated Pullcord Passive Vent | C59: =_xlfn.CONCAT(A59," - Materials") -> Condensation control: Supply and install Dryaire Cpass Insulated Pullcord Passive Vent - Materials | D59: 1 | E59: =N59 -> 0 | F59: EACH | G59: Condensation Materials | H59: =((P59-N59)/N59)*100 -> #DIV/0! | I59: % | J59: MTL | K59: Yes | L59: ='Customer Summary'!D7 -> No | M59: =IF(J59="MTL","Preservation Shop","") -> Preservation Shop | N59: =SUM(N55:N56) -> 0 | O59: =IF(N59=0,"DELETE","LEAVE") -> DELETE | P59: =SUM(P55:P56) -> 0 | Q59: Yes
A60: =A59 -> Condensation control: Supply and install Dryaire Cpass Insulated Pullcord Passive Vent | C60: =_xlfn.CONCAT(A60," - Labour") -> Condensation control: Supply and install Dryaire Cpass Insulated Pullcord Passive Vent - Labour | D60: =SUM(D57:D58) -> 0 | E60: =N60/D60 -> #DIV/0! | F60: Hours | G60: Condensation Labour | H60: =((P60-N60)/N60)*100 -> #DIV/0! | I60: % | J60: LBR | K60: Yes | L60: =L59 -> No | M60: =IF(J60="MTL","Preservation Shop","") | N60: =SUM(N57:N58) -> 0 | O60: =IF(N60=0,"DELETE","LEAVE") -> DELETE | P60: =SUM(P57:P58) -> 0 | Q60: Yes
O61: DELETE
A62: ='Customer Summary'!C8 -> Condensation control: Supply and install Dryaire CVent | C62: =Costing!B57 -> Dryaire Cvent | D62: =Costing!F57 -> 0 | E62: =Costing!I57 -> 12.5 | F62: =Costing!G57 -> Each | G62: Condensation Materials | H62: =Costing!J57*100 -> 30 | I62: % | J62: MTL | K62: Yes | L62: No | M62: =IF(J62="MTL","Preservation Shop","") -> Preservation Shop | N62: =D62*E62 -> 0 | O62: DELETE | P62: =N62*(1+(H62/100)) -> 0 | Q62: No
A63: =A62 -> Condensation control: Supply and install Dryaire CVent | C63: =Costing!B58 -> Diamond core 107mm hole | D63: =Costing!F58 -> 0 | E63: =Costing!I58 -> 0 | F63: =Costing!G58 -> Each | G63: Condensation Materials | H63: =Costing!J58*100 -> 30 | I63: % | J63: MTL | K63: Yes | L63: No | M63: =IF(J63="MTL","Preservation Shop","") -> Preservation Shop | N63: =D63*E63 -> 0 | O63: DELETE | P63: =N63*(1+(H63/100)) -> 0 | Q63: No
A64: =A63 -> Condensation control: Supply and install Dryaire CVent | C64: =Costing!M57 -> Dryaire Cvent | D64: =Costing!O57 -> 0 | E64: =Costing!Q57 -> 30.63 | F64: Hours | G64: Condensation Labour | H64: =Costing!R57*100 -> 100 | I64: % | J64: LBR | K64: Yes | L64: No | M64: =IF(J64="MTL","Preservation Shop","") | N64: =D64*E64 -> 0 | O64: DELETE | P64: =N64*(1+(H64/100)) -> 0 | Q64: No
A65: =A64 -> Condensation control: Supply and install Dryaire CVent | C65: =Costing!M58 -> Diamond core 107mm hole | D65: =Costing!O58 -> 0 | E65: =Costing!Q58 -> 30.63 | F65: Hours | G65: Condensation Labour | H65: =Costing!R58*100 -> 100 | I65: % | J65: LBR | K65: Yes | L65: No | M65: =IF(J65="MTL","Preservation Shop","") | N65: =D65*E65 -> 0 | O65: DELETE | P65: =N65*(1+(H65/100)) -> 0 | Q65: No
A66: =A65 -> Condensation control: Supply and install Dryaire CVent | C66: =_xlfn.CONCAT(A66," - Materials") -> Condensation control: Supply and install Dryaire CVent - Materials | D66: 1 | E66: =N66 -> 0 | F66: EACH | G66: Condensation Materials | H66: =((P66-N66)/N66)*100 -> #DIV/0! | I66: % | J66: MTL | K66: Yes | L66: ='Customer Summary'!D8 -> No | M66: =IF(J66="MTL","Preservation Shop","") -> Preservation Shop | N66: =SUM(N62:N63) -> 0 | O66: =IF(N66=0,"DELETE","LEAVE") -> DELETE | P66: =SUM(P62:P63) -> 0 | Q66: Yes
A67: =A66 -> Condensation control: Supply and install Dryaire CVent | C67: =_xlfn.CONCAT(A67," - Labour") -> Condensation control: Supply and install Dryaire CVent - Labour | D67: 1 | E67: =N67/D67 -> 0 | F67: Hours | G67: Condensation Labour | H67: =((P67-N67)/N67)*100 -> #DIV/0! | I67: % | J67: LBR | K67: Yes | L67: =L66 -> No | M67: =IF(J67="MTL","Preservation Shop","") | N67: =SUM(N64:N65) -> 0 | O67: =IF(N67=0,"DELETE","LEAVE") -> DELETE | P67: =SUM(P64:P65) -> 0 | Q67: Yes
D68: =SUM(D64:D65) -> 0 | O68: DELETE
A69: ='Customer Summary'!C14 -> Airbricks | C69: =Costing!B82 -> Clean out airbrick/fit new face | D69: =Costing!F82 -> 0 | E69: =Costing!I82 -> 16 | F69: =Costing!G82 -> Each | G69: Condensation Materials | H69: =Costing!J82*100 -> 30 | I69: % | J69: MTL | K69: Yes | L69: No | M69: =IF(J69="MTL","Preservation Shop","") -> Preservation Shop | N69: =D69*E69 -> 0 | O69: DELETE | P69: =N69*(1+(H69/100)) -> 0 | Q69: No
A70: =A69 -> Airbricks | C70: =Costing!B83 -> Lift/upgrade existing airbrick/fit new face | D70: =Costing!F83 -> 0 | E70: =Costing!I83 -> 16 | F70: =Costing!G83 -> Each | G70: Condensation Materials | H70: =Costing!J83*100 -> 30 | I70: % | J70: MTL | K70: Yes | L70: No | M70: =IF(J70="MTL","Preservation Shop","") -> Preservation Shop | N70: =D70*E70 -> 0 | O70: DELETE | P70: =N70*(1+(H70/100)) -> 0 | Q70: No
A71: =A70 -> Airbricks | C71: =Costing!B84 -> Install additional airbrick | D71: =Costing!F84 -> 0 | E71: =Costing!I84 -> 16 | F71: =Costing!G84 -> Each | G71: Condensation Materials | H71: =Costing!J84*100 -> 30 | I71: % | J71: MTL | K71: Yes | L71: No | M71: =IF(J71="MTL","Preservation Shop","") -> Preservation Shop | N71: =D71*E71 -> 0 | O71: DELETE | P71: =N71*(1+(H71/100)) -> 0 | Q71: No
A72: =A71 -> Airbricks | C72: =Costing!M82 -> Clean out airbrick/fit new face | D72: =Costing!O82 -> 0 | E72: =Costing!Q82 -> 30.63 | F72: Hours | G72: Condensation Labour | H72: =Costing!R82*100 -> 100 | I72: % | J72: LBR | K72: Yes | L72: No | M72: =IF(J72="MTL","Preservation Shop","") | N72: =D72*E72 -> 0 | O72: DELETE | P72: =N72*(1+(H72/100)) -> 0 | Q72: No
A73: =A72 -> Airbricks | C73: =Costing!M83 -> Lift/upgrade existing airbrick/fit new face | D73: =Costing!O83 -> 0 | E73: =Costing!Q83 -> 30.63 | F73: Hours | G73: Condensation Labour | H73: =Costing!R83*100 -> 100 | I73: % | J73: LBR | K73: Yes | L73: No | M73: =IF(J73="MTL","Preservation Shop","") | N73: =D73*E73 -> 0 | O73: DELETE | P73: =N73*(1+(H73/100)) -> 0 | Q73: No
A74: =A73 -> Airbricks | C74: =Costing!M84 -> Install additional airbrick | D74: =Costing!O84 -> 0 | E74: =Costing!Q84 -> 30.63 | F74: Hours | G74: Condensation Labour | H74: =Costing!R84*100 -> 100 | I74: % | J74: LBR | K74: Yes | L74: No | M74: =IF(J74="MTL","Preservation Shop","") | N74: =D74*E74 -> 0 | O74: DELETE | P74: =N74*(1+(H74/100)) -> 0 | Q74: No
A75: =A74 -> Airbricks | C75: =_xlfn.CONCAT(A75," - Materials") -> Airbricks - Materials | D75: 1 | E75: =N75 -> 0 | F75: EACH | G75: Condensation Materials | H75: =((P75-N75)/N75)*100 -> #DIV/0! | I75: % | J75: MTL | K75: Yes | L75: ='Customer Summary'!D14 -> No | M75: =IF(J75="MTL","Preservation Shop","") -> Preservation Shop | N75: =SUM(N69:N71) -> 0 | O75: =IF(N75=0,"DELETE","LEAVE") -> DELETE | P75: =SUM(P69:P71) -> 0 | Q75: Yes
A76: =A75 -> Airbricks | C76: =_xlfn.CONCAT(A76," - Labour") -> Airbricks - Labour | D76: =SUM(D72:D74) -> 0 | E76: =N76/D76 -> #DIV/0! | F76: Hours | G76: Condensation Labour | H76: =((P76-N76)/N76)*100 -> #DIV/0! | I76: % | J76: LBR | K76: Yes | L76: =L75 -> No | M76: =IF(J76="MTL","Preservation Shop","") | N76: =SUM(N72:N74) -> 0 | O76: =IF(N76=0,"DELETE","LEAVE") -> DELETE | P76: =SUM(P72:P74) -> 0 | Q76: Yes
O77: DELETE
A78: ='Customer Summary'!C9 -> Joinery: Supply and fit boxwork for ducting | C78: =_xlfn.CONCAT(A78," - Materials") -> Joinery: Supply and fit boxwork for ducting - Materials | D78: =Costing!F62 -> 0 | E78: =Costing!I62 -> 0 | F78: =Costing!G66 -> Each | G78: Condensation Materials | H78: =Costing!J62*100 -> 30 | I78: % | J78: MTL | K78: Yes | L78: ='Customer Summary'!D9 -> Yes | M78: =IF(J78="MTL","Preservation Shop","") -> Preservation Shop | N78: =D78*E78 -> 0 | O78: =IF(N78=0,"DELETE","LEAVE") -> DELETE | P78: =N78*(1+(H78/100)) -> 0 | Q78: Yes
A79: =A78 -> Joinery: Supply and fit boxwork for ducting | C79: =_xlfn.CONCAT(A79," - Labour") -> Joinery: Supply and fit boxwork for ducting - Labour | D79: =Costing!O62 -> 0 | E79: =Costing!Q62 -> 30.63 | F79: Hours | G79: Condensation Labour | H79: =Costing!R62*100 -> 100 | I79: % | J79: LBR | K79: Yes | L79: =L78 -> Yes | M79: =IF(J79="MTL","Preservation Shop","") | N79: =D79*E79 -> 0 | O79: =IF(N79=0,"DELETE","LEAVE") -> DELETE | P79: =N79*(1+(H79/100)) -> 0 | Q79: Yes
O80: DELETE
A81: ='Customer Summary'!C10 -> New hatch and ladder: Create larger opening, install new sturdy hatch and ladder to loft entry | C81: =_xlfn.CONCAT(A81," - Materials") -> New hatch and ladder: Create larger opening, install new sturdy hatch and ladder to loft entry - Materials | D81: =Costing!F66 -> 0 | E81: =Costing!I66 -> 360 | F81: =Costing!G66 -> Each | G81: Condensation Materials | H81: =Costing!J66*100 -> 30 | I81: % | J81: MTL | K81: Yes | L81: ='Customer Summary'!D10 -> Yes | M81: =IF(J81="MTL","Preservation Shop","") -> Preservation Shop | N81: =D81*E81 -> 0 | O81: =IF(N81=0,"DELETE","LEAVE") -> DELETE | P81: =N81*(1+(H81/100)) -> 0 | Q81: Yes
A82: =A81 -> New hatch and ladder: Create larger opening, install new sturdy hatch and ladder to loft entry | C82: =_xlfn.CONCAT(A82," - Labour") -> New hatch and ladder: Create larger opening, install new sturdy hatch and ladder to loft entry - Labour | D82: =Costing!O66 -> 0 | E82: =Costing!Q66 -> 30.63 | F82: Hours | G82: Condensation Labour | H82: =Costing!R66*100 -> 100 | I82: % | J82: LBR | K82: Yes | L82: =L81 -> Yes | M82: =IF(J82="MTL","Preservation Shop","") | N82: =D82*E82 -> 0 | O82: =IF(N82=0,"DELETE","LEAVE") -> DELETE | P82: =N82*(1+(H82/100)) -> 0 | Q82: Yes
O83: DELETE
A84: ='Customer Summary'!C11 -> Loft opening: Enlarge existing loft opening and install new hatch lid | C84: =_xlfn.CONCAT(A84," - Materials") -> Loft opening: Enlarge existing loft opening and install new hatch lid - Materials | D84: =Costing!F70 -> 0 | E84: =Costing!I70 -> 45 | F84: =Costing!G70 -> Each | G84: Condensation Materials | H84: =Costing!J70*100 -> 30 | I84: % | J84: MTL | K84: Yes | L84: ='Customer Summary'!D11 -> Yes | M84: =IF(J84="MTL","Preservation Shop","") -> Preservation Shop | N84: =D84*E84 -> 0 | O84: =IF(N84=0,"DELETE","LEAVE") -> DELETE | P84: =N84*(1+(H84/100)) -> 0 | Q84: Yes
A85: =A84 -> Loft opening: Enlarge existing loft opening and install new hatch lid | C85: =_xlfn.CONCAT(A85," - Labour") -> Loft opening: Enlarge existing loft opening and install new hatch lid - Labour | D85: =Costing!O70 -> 0 | E85: =Costing!Q70 -> 30.63 | F85: Hours | G85: Condensation Labour | H85: =Costing!R70*100 -> 100 | I85: % | J85: LBR | K85: Yes | L85: =L84 -> Yes | M85: =IF(J85="MTL","Preservation Shop","") | N85: =D85*E85 -> 0 | O85: =IF(N85=0,"DELETE","LEAVE") -> DELETE | P85: =N85*(1+(H85/100)) -> 0 | Q85: Yes
O86: DELETE
A87: ='Customer Summary'!C12 -> Remedial treatments: Mould treatment | C87: =_xlfn.CONCAT(A87," - Materials") -> Remedial treatments: Mould treatment - Materials | D87: =Costing!F74 -> 6 | E87: =Costing!I74 -> 0.5 | F87: =Costing!G74 -> M2 | G87: Condensation Materials | H87: =Costing!J74*100 -> 30 | I87: % | J87: MTL | K87: Yes | L87: ='Customer Summary'!D12 -> No | M87: =IF(J87="MTL","Preservation Shop","") -> Preservation Shop | N87: =D87*E87 -> 3 | O87: =IF(N87=0,"DELETE","LEAVE") -> LEAVE | P87: =N87*(1+(H87/100)) -> 3.9 | Q87: Yes
A88: =A87 -> Remedial treatments: Mould treatment | C88: =_xlfn.CONCAT(A88," - Labour") -> Remedial treatments: Mould treatment - Labour | D88: =Costing!O74 -> 1.5 | E88: =Costing!Q74 -> 30.63 | F88: Hours | G88: Condensation Labour | H88: =Costing!R74*100 -> 100 | I88: % | J88: LBR | K88: Yes | L88: =L87 -> No | M88: =IF(J88="MTL","Preservation Shop","") | N88: =D88*E88 -> 45.945 | O88: =IF(N88=0,"DELETE","LEAVE") -> LEAVE | P88: =N88*(1+(H88/100)) -> 91.89 | Q88: Yes
O89: DELETE
A90: ='Customer Summary'!C13 -> Asbestos Testing | C90: =_xlfn.CONCAT(A90," - Materials") -> Asbestos Testing - Materials | D90: =Costing!F78 -> 0 | E90: =Costing!I78 -> 30 | F90: =Costing!G78 -> Each | G90: Condensation Materials | H90: =Costing!J78*100 -> 30 | I90: % | J90: MTL | K90: Yes | L90: ='Customer Summary'!D13 -> Yes | M90: =IF(J90="MTL","Preservation Shop","") -> Preservation Shop | N90: =D90*E90 -> 0 | O90: =IF(N90=0,"DELETE","LEAVE") -> DELETE | P90: =N90*(1+(H90/100)) -> 0 | Q90: Yes
A91: =A90 -> Asbestos Testing | C91: =_xlfn.CONCAT(A91," - Labour") -> Asbestos Testing - Labour | D91: =Costing!O78 -> 0 | E91: =Costing!Q78 -> 30.63 | F91: Hours | G91: Condensation Labour | H91: =Costing!R78*100 -> 100 | I91: % | J91: LBR | K91: Yes | L91: =L90 -> Yes | M91: =IF(J91="MTL","Preservation Shop","") | N91: =D91*E91 -> 0 | O91: =IF(N91=0,"DELETE","LEAVE") -> DELETE | P91: =N91*(1+(H91/100)) -> 0 | Q91: Yes
O92: DELETE
A93: ='Customer Summary'!C15 -> Project Specific Overheads | C93: Skips | D93: =Costing!F88 -> 0 | E93: =Costing!I88 -> 270 | F93: Each | G93: Waste Removal | H93: =Costing!J88*100 -> 30 | I93: % | J93: Other | K93: Yes | L93: No | M93: =IF(J93="MTL","Preservation Shop","") | N93: =D93*E93 -> 0 | O93: DELETE | P93: =N93*(1+(H93/100)) -> 0 | Q93: No
A94: =A93 -> Project Specific Overheads | C94: Vehicle Costs (Fuel) | D94: =Costing!K98*Costing!K99*2 -> 92 | E94: =Costing!J107 -> 0.5 | F94: Miles | G94: Travel Costs | H94: 0 | I94: % | J94: Other | K94: Yes | L94: No | M94: =IF(J94="MTL","Preservation Shop","") | N94: =D94*E94 -> 46 | O94: DELETE | P94: =N94*(1+(H94/100)) -> 46 | Q94: No
A95: =A94 -> Project Specific Overheads | C95: Travel Costs for Tradesmen | D95: =Costing!O93 -> 3.0666667 | E95: =Costing!C107 -> 30.63 | F95: Hours | G95: Travel Costs | H95: 0 | I95: % | J95: LBR | K95: Yes | L95: No | M95: =IF(J95="MTL","Preservation Shop","") | N95: =D95*E95 -> 93.932 | O95: DELETE | P95: =N95*(1+(H95/100)) -> 93.932 | Q95: No
A96: =A95 -> Project Specific Overheads | B96: (May cover any or all of the following: Covers Health & Safety, Tooling Equipment, Access Equipment, Specialist Equipment, Waste Removal & Disposal, Project Management Administration etc.) | C96: =_xlfn.CONCAT(A96," - Materials") -> Project Specific Overheads - Materials | D96: 1 | E96: =N96 -> 46 | F96: EACH | G96: Condensation Materials | H96: =((P96-N96)/N96)*100 -> 0 | I96: % | J96: MTL | K96: Yes | L96: No | M96: =IF(J96="MTL","Preservation Shop","") -> Preservation Shop | N96: =SUM(N93:N94) -> 46 | O96: =IF(N96=0,"DELETE","LEAVE") -> LEAVE | P96: =SUM(P93:P94) -> 46 | Q96: Yes
A97: =A96 -> Project Specific Overheads | B97: (May cover any or all of the following: Covers Health & Safety, Tooling Equipment, Access Equipment, Specialist Equipment, Waste Removal & Disposal, Project Management Administration etc.) | C97: =_xlfn.CONCAT(A97," - Labour") -> Project Specific Overheads - Labour | D97: =D95 -> 3.0666667 | E97: =E95 -> 30.63 | F97: =F95 -> Hours | G97: Condensation Labour | H97: =H95 -> 0 | I97: % | J97: =J95 -> LBR | K97: =K95 -> Yes | L97: No | M97: =IF(J97="MTL","Preservation Shop","") | N97: =N95 -> 93.932 | O97: =IF(N97=0,"DELETE","LEAVE") -> LEAVE | P97: =P95 -> 93.932 | Q97: Yes

Sheet Data Lists
A1: Data Lists For Contractor Foreman
A3: These are used to differentiate between the types of items and used for the labor calculations.
A4: Contractor Foreman Item Types
A5: Item | B5: Comments
A6: EQUIP | B6: Equipment Items
A7: LBR | B7: Labor items
A8: MTL | B8: Material Items
A9: Other | B9: Other Items
A10: SUB | B10: Subcontractors
A12: This is used to 'Group' items in a logical order on the estimate.
A13: Sections
A14: Item | B14: Comments
A15: ='Customer Summary'!C4 -> Condensation control: Supply and install Loft Dryaire system & required accessories | B15: n/a
A16: ='Customer Summary'!C5 -> Condensation control: Supply and install Wall Mounted Dryaire system & required accessories | B16: n/a
A17: ='Customer Summary'!C6 -> Condensation control: Supply and install Trickle & Boost Fan | B17: n/a
A18: ='Customer Summary'!C7 -> Condensation control: Supply and install Dryaire Cpass Insulated Pullcord Passive Vent | B18: n/a
A19: ='Customer Summary'!C8 -> Condensation control: Supply and install Dryaire CVent | B19: n/a
A20: ='Customer Summary'!C14 -> Airbricks | B20: n/a
A21: ='Customer Summary'!C9 -> Joinery: Supply and fit boxwork for ducting | B21: n/a
A22: ='Customer Summary'!C10 -> New hatch and ladder: Create larger opening, install new sturdy hatch and ladder to loft entry | B22: n/a
A23: ='Customer Summary'!C11 -> Loft opening: Enlarge existing loft opening and install new hatch lid | B23: n/a
A24: ='Customer Summary'!C12 -> Remedial treatments: Mould treatment | B24: n/a
A25: ='Customer Summary'!C13 -> Asbestos Testing | B25: n/a
A26: ='Customer Summary'!C15 -> Project Specific Overheads | B26: n/a
A33: This is used in the projects to determine costs by the 'Cost Code' category (lets you see which areas you are over or under budget on).
A34: Cost Codes
A35: Item | B35: Comments
A36: Condensation Equipment | B36: n/a
A37: Condensation Labour | B37: n/a
A38: Condensation Materials | B38: n/a
A39: Condensation Other | B39: n/a
A40: Condensation Sub Contractors | B40: n/a
A41: Travel Costs | B41: n/a
A42: Waste Removal | B42: n/a
A45: This is used to on the items for costing reference
A46: Unit of measures
A47: Item | B47: Comments
A48: Each | B48: n/a
A49: M2 | B49: n/a
A50: M3 | B50: n/a
A51: Hours | B51: n/a
A52: LM | B52: n/a
A53: Miles | B53: n/a
A54: Bags | B54: n/a
A55: Pairs | B55: n/a
A58: CSV Import File Name Creator
A59: CSV File Name | B59: CF-Condensation-PIV-
A60: Current Date | B60: 25-11-25-14-57-56
A61: Full File Name | B61: =CONCATENATE(B59,B60) -> CF-Condensation-PIV-25-11-25-14-57-56
A63: File Name Creator
A64: PDF Report Name | B64: =CONCATENATE(Costing!E4,"-CONDENSATION-PIV-REPORT-",B60) -> PRONE455DN-CONDENSATION-PIV-REPORT-25-11-25-14-57-56
A66: Section Price Adjustment % Values
A67: -5
A68: =A67+1 -> -4
A69: =A68+1 -> -3
A70: =A69+1 -> -2
A71: =A70+1 -> -1
A72: =A71+1 -> 0
A73: =A72+1 -> 1
A74: =A73+1 -> 2
A75: =A74+1 -> 3
A76: =A75+1 -> 4
A77: =A76+1 -> 5
A78: =A77+1 -> 6
A79: =A78+1 -> 7
... A122: =A121+1 -> 50

Sheet Changes
A1: Date | B1: Version From | C1: Version To | D1: Change
A2: 45393 | B2: 17 | C2: 18 | D2: Add VBA to updated the file name (date) on each click as the file names only changed on open so if clicking multiple times it was trying to save the same file again which is confusing)
A3: 45393 | B3: 17 | C3: 18 | D3: Added Sub Contractor 'clarity' section on costing sheet - Vat registered and non vat registered
A4: 45425 | B4: 18 | C4: 19 | D4: Added the word trunking along with ducting etc.
A5: 45440 | B5: 19 | C5: 20 | D5: Changed ambiguous wording to roof vents to 'Customer to …'.
A6: 45440 | B6: 19 | C6: 20 | D6: Added deposit value ex vat and inc vat for card readers.
A7: 45460 | B7: 20 | C7: 21 | D7: Added Section Price Adjustment %.
A8: 45489 | B8: 21 | C8: 22 | D8: Added external defects & airbricks section to the report.
A9: 45491 | B9: 22 | C9: 23 | D9: Re-arranged the external defects section to be put at the bottom of the report.
A10: 45495 | B10: 23 | C10: 24 | D10: Fixed conditional logic issue which was showing a row on the report when it shouldn't have been.
A11: 45539 | B11: 25 | C11: 26 | D11: Added conditional logic to Defects section on report so that it pre-populates more cells as requested by GH. Also removed the Office comments section at the bottom of the report as it is hiiden when the filter is applied so this is replaced with an 'Office Notes' tab.
A12: 45562 | B12: 26 | C12: 27 | D12: Changed wording on Projects Specific Overheads to make it look more generic and to cover more areas and removed the vehicle costs statement. Added the On Site Approval Form Tab.
A13: 45600 | B13: 27 | C13: 28 | D13: Increased rate from £30 to £30.63 to cover for Employers NI increase.
... A22: 45974 | B22: 36 | C22: 37 | D22: Updated master password.
